[
  {
    "images": [
      "https://i.ibb.co/vsft5xb/priyanka-mohan-sreekaram-grand-release5.jpg",
      "https://i.ibb.co/rcrk6Qt/00004-2049397919.png"
    ],
    "title": "Priyanka Mohan ai fake",
    "pg": "1"
  },
  {
    "images": [
      "https://i.ibb.co/ZH4BgvJ/trisha216.jpg",
      "https://i.ibb.co/2tDtd4D/00000-1324469489-copy.png"
    ],
    "title": "Trisha krishnan",
    "pg": "1"
  },
  {
    "images": [
      "https://i.ibb.co/HqkZFF7/trisha128.jpg",
      "https://i.ibb.co/3NnWV7Q/00008-1899712474-copy.png"
    ],
    "title": "Trisha krishnan",
    "pg": "1"
  },
  {
    "images": [
      "https://i.ibb.co/LpcXM5L/trisha2918.jpg",
      "https://i.ibb.co/7g1p4T6/00005-1553317292-copy.png"
    ],
    "title": "Trisha krishnan",
    "pg": "1"
  },
  {
    "images": [
      "https://i.ibb.co/B27Mhzb/trisha716.jpg",
      "https://i.ibb.co/jw4Wh8d/00004-3762682967-copy.png"
    ],
    "title": "Trisha krishnan marijuana policy project",
    "pg": "1"
  },
  {
    "images": [
      "https://i.ibb.co/qdc0qrZ/trisha572.jpg",
      "https://i.ibb.co/DkGZ4SY/00003-946157691-copy.png"
    ],
    "title": "Trisha krishnan valley family church",
    "pg": "1"
  },
  {
    "images": [
      "https://i.ibb.co/xfkDNyq/FB-IMG-1682270000473.jpg",
      "https://i.ibb.co/82fwh8G/00002-2047519714-copy.png"
    ],
    "title": "Trisha krishnan",
    "pg": "1"
  },
  {
    "images": [
      "https://i.ibb.co/5nMYhgw/342378222-608847687809303-5462081722984040618-n.jpg",
      "https://i.ibb.co/5LsS0k6/00001-727151575-copy.png"
    ],
    "title": "Trisha krishnan",
    "pg": "1"
  },
  {
    "images": [
      "https://i.ibb.co/zHy2Cqz/trisha553.jpg",
      "https://i.ibb.co/Ttxzmmx/00000-2945958610-copy.png"
    ],
    "title": "Trisha krishnan",
    "pg": "1"
  },
  {
    "images": [
      "https://i.ibb.co/8s9YbGs/priyanka-arul-mohan-et-pre-release1.jpg",
      "https://i.ibb.co/5TJX0fY/00009-83811248-copy.jpg"
    ],
    "title": "priyanka mohan",
    "pg": "1"
  },
  {
    "images": [
      "https://i.ibb.co/fpxs0Jr/priyanka-arul-mohan-varun-doctor-interview13.jpg",
      "https://i.ibb.co/Nr2rn1G/00012-1910062561-copy.png"
    ],
    "title": "priyanka mohan william james college",
    "pg": "1"
  },
  {
    "images": [
      "https://i.ibb.co/JchSLWV/priyanka-mohan-sreekaram-pre-release1.jpg",
      "https://i.ibb.co/txMZdm9/00013-4117117664-copy.png"
    ],
    "title": "priyanka mohan",
    "pg": "1"
  },
  {
    "images": [
      "https://i.ibb.co/s9rMRs9/wallpaperflare-cropped.jpg",
      "https://i.ibb.co/h1xMMBW/00014-3627192369-copy.png"
    ],
    "title": "kajal agarwal humane society honolulu",
    "pg": "1"
  },
  {
    "images": [
      "https://i.ibb.co/jf5R7sc/download.jpg",
      "https://i.ibb.co/1QGhVFd/00015-3802197202-copy.png"
    ],
    "title": "tamanna family healthcare network visalia ca",
    "pg": "1"
  },
  {
    "images": [
      "https://i.ibb.co/HCQm8f6/peakpx-2.jpg",
      "https://i.ibb.co/ZKqVV1p/00017-584509029-copy.png"
    ],
    "title": "priyanka mohan",
    "pg": "1"
  },
  {
    "images": [
      "https://i.ibb.co/qNjNBmH/peakpx-1.jpg",
      "https://i.ibb.co/4Zz5pGL/00018-3492855796-copy.png"
    ],
    "title": "",
    "pg": "2"
  },
  {
    "images": [
      "https://i.ibb.co/5nLfDGy/HD-wallpaper-priya-bhavani-shankar-dress-thigh.jpg",
      "https://i.ibb.co/2ggFzcy/00017-1283329593-copy.png"
    ],
    "title": "priya bhavani shankar",
    "pg": "2"
  },
  {
    "images": [
      "https://i.ibb.co/vYSgtqV/HD-wallpaper-priya-bhavani-shankar-eye-dress.jpg",
      "https://i.ibb.co/MkNGb8S/00015-2111546411-copy.png"
    ],
    "title": "priya bhavani shankar how to fix the resolution on my computer",
    "pg": "2"
  },
  {
    "images": [
      "https://i.ibb.co/hWhwVyx/peakpx-9.jpg",
      "https://i.ibb.co/f0xtYb9/00013-190156232-copy.png"
    ],
    "title": "priyanka mohan",
    "pg": "2"
  },
  {
    "images": [
      "https://i.ibb.co/p0gm4Sz/HD-wallpaper-shivani-narayanan-joint-muscle.jpg",
      "https://i.ibb.co/d6gVhpD/00010-602149603-copy.png"
    ],
    "title": "",
    "pg": "2"
  },
  {
    "images": [
      "https://i.ibb.co/y07rJv5/peakpx-11.jpg",
      "https://i.ibb.co/6y6dX3f/00012-3438162291-copy.png"
    ],
    "title": "Raashii Khanna what is screen resolution",
    "pg": "2"
  },
  {
    "images": [
      "https://i.ibb.co/9ZG6QgH/HD-wallpaper-athulya-ravi-eye-head.jpg",
      "https://i.ibb.co/zJW1Bm3/00028-1029067020-copy.png"
    ],
    "title": "Athulya ravi ai fakes[/Athulya ravi nude pics] \u200b",
    "pg": "2"
  },
  {
    "images": [
      "https://i.ibb.co/1XQD3mk/HD-wallpaper-athulya-ravi-athulya-ravi.jpg",
      "https://i.ibb.co/frK4sGS/00027-689399569-copy.png"
    ],
    "title": "Athulya ravi",
    "pg": "2"
  },
  {
    "images": [
      "https://i.ibb.co/SNPp506/HD-wallpaper-regina-cassandra-actress-reginacassandra-tamil-telugu.jpg",
      "https://i.ibb.co/bg9TLkN/00026-3689213302-copy.png"
    ],
    "title": "Regina Cassandra",
    "pg": "2"
  },
  {
    "images": [
      "https://i.ibb.co/MVpmvR1/HD-wallpaper-keerthy-suresh-actress-keerthi-keerthi-suresh-keerthisuresh-keerthysuresh-tamil-telugu.jpg",
      "https://i.ibb.co/0BZVGLt/00025-3200387778-copy.png"
    ],
    "title": "keerthy suresh",
    "pg": "2"
  },
  {
    "images": [
      "https://i.ibb.co/6tzF2zf/HD-wallpaper-keerthi-suresh-actress-keerthisuresh-keerthy-keerthy-suresh-keerthysuresh-tamil-telugu.jpg",
      "https://i.ibb.co/5cDjrVJ/00024-3453873797-copy.png"
    ],
    "title": "keerthy suresh",
    "pg": "2"
  },
  {
    "images": [
      "https://i.ibb.co/WGmPdZR/HD-wallpaper-keerthy-suresh-actress-keerthi-keerthi-suresh-keerthisuresh-keerthysuresh-malayalam-mov.jpg",
      "https://i.ibb.co/VVQ871B/00023-3174708963-copy.png"
    ],
    "title": "keerthy suresh most popular poems to memorize",
    "pg": "2"
  },
  {
    "images": [
      "https://i.ibb.co/2Mwj3KF/HD-wallpaper-keerthy-suresh-actress-keerthi-keerthi-suresh-keerthisuresh-keerthysuresh-malayalam-tam.jpg",
      "https://i.ibb.co/qyqLMwK/00022-3450343490-copy.png"
    ],
    "title": "keerthy suresh",
    "pg": "2"
  },
  {
    "images": [
      "https://i.ibb.co/Cnybyzz/HD-wallpaper-keerthysuresh-actress-keerthi-keerthi-suresh-keerthisuresh-keerthy-keerthy-suresh-tamil.jpg",
      "https://i.ibb.co/d4m4xL7/00021-561430815-copy.png"
    ],
    "title": "keerthy suresh",
    "pg": "2"
  },
  {
    "images": [
      "https://i.ibb.co/DzwXDk5/HD-wallpaper-richa-gangopadhyay-multilingual-actress-osthe-tamil-movie.jpg",
      "https://i.ibb.co/qM0X8x1/00020-650480990-copy.png"
    ],
    "title": "richa gangopadhyay",
    "pg": "2"
  },
  {
    "images": [
      "https://i.ibb.co/tzHCC9p/HD-wallpaper-nivetha-pethuraj-alluarjun-avpl-dusky-heroine-kollywood-saree-tamilnadu-tollywood-tradi.jpg",
      "https://i.ibb.co/Ks1GCjc/00019-1645337809-copy.png"
    ],
    "title": "nivetha pethuraj",
    "pg": "2"
  },
  {
    "images": [
      "https://i.ibb.co/4gXqxJM/HD-wallpaper-nivetha-pethuraj-actress-tamil.jpg",
      "https://i.ibb.co/qxZV74M/00018-3078386819-copy.png"
    ],
    "title": "nivetha pethuraj good easy poems",
    "pg": "2"
  },
  {
    "images": [
      "https://i.ibb.co/m4RdcXH/HD-wallpaper-nivetha-pethuraj-nivetha-pethuraj-tamil-actress.jpg",
      "https://i.ibb.co/02GXnXW/00017-85522865-copy.png"
    ],
    "title": "nivetha pethuraj",
    "pg": "2"
  },
  {
    "images": [
      "https://i.ibb.co/LtGBpH8/HD-wallpaper-nayanthara-telugu-actress-tamil-actress.jpg",
      "https://i.ibb.co/ThKSbq8/00016-1732595359-copy.png"
    ],
    "title": "nayanthara",
    "pg": "3"
  },
  {
    "images": [
      "https://i.ibb.co/1mMxQYp/HD-wallpaper-nayanthara-actress-helena-kerala-kollywood-mallu-samantha-saree-seeta-tollywood.jpg",
      "https://i.ibb.co/F5kZb3p/00015-575318068-copy.png"
    ],
    "title": "nayanthara",
    "pg": "3"
  },
  {
    "images": [
      "https://i.ibb.co/8XFQ16p/HD-wallpaper-anushka-shetty-akhilanda-telugu.jpg",
      "https://i.ibb.co/RH4mmQJ/00012-594010484-copy.png"
    ],
    "title": "anushka shetty",
    "pg": "3"
  },
  {
    "images": [
      "https://i.ibb.co/frwYQ2n/HD-wallpaper-anushka-shetty-beautiful-rudhramadevi.jpg",
      "https://i.ibb.co/ctcM7dH/00010-686655297-copy.png"
    ],
    "title": "anushka shetty poems about strength and love",
    "pg": "3"
  },
  {
    "images": [
      "https://i.ibb.co/Kb3HT21/madonna-sebastian-latest-photos-08-005.jpg",
      "https://i.ibb.co/4KK73QZ/00008-2941036518-copy.png"
    ],
    "title": "Madonna Sebastian",
    "pg": "3"
  },
  {
    "images": [
      "https://i.ibb.co/XJbJbN9/peakpx-4.jpg",
      "https://i.ibb.co/Q8kZsTd/00007-609620280-copy.png"
    ],
    "title": "Trisha krishnan",
    "pg": "3"
  },
  {
    "images": [
      "https://i.ibb.co/nP92pzQ/peakpx-2.jpg",
      "https://i.ibb.co/26qmG9H/00006-1355908578-copy.png"
    ],
    "title": "Nabha Natesh",
    "pg": "3"
  },
  {
    "images": [
      "https://i.ibb.co/gWTs59c/HD-wallpaper-nabha-natesh-disco-raja-nabha-tollywood.jpg",
      "https://i.ibb.co/MG02xNV/00004-2896308373-copy.png"
    ],
    "title": "Nabha Natesh george eliot poems",
    "pg": "3"
  },
  {
    "images": [
      "https://i.ibb.co/hg2ppcv/peakpx-1.jpg",
      "https://i.ibb.co/8gVy4P6/00005-2334447938-copy.png"
    ],
    "title": "Ritika Singh i carry your heart with me theme",
    "pg": "3"
  },
  {
    "images": [
      "https://i.ibb.co/CB06JBw/peakpx.jpg",
      "https://i.ibb.co/9HN7GL3/00001-3262936229-copy.png"
    ],
    "title": "Ritika Singh the unknown citizen poem meaning",
    "pg": "3"
  },
  {
    "images": [
      "https://i.ibb.co/yXJ7BPn/pavithra-lakshmi-stills-photos-pictures-107.jpg",
      "https://i.ibb.co/MS1jBwn/00004-4040099344-copy.png"
    ],
    "title": "Pavithra lakshmi",
    "pg": "3"
  },
  {
    "images": [
      "https://i.ibb.co/sqBxfSn/HD-wallpaper-pavithra-lakshmi-actress-black-hair-beauty-sad-bollywood-portrait-elegant-indian.jpg",
      "https://i.ibb.co/9tGVMhV/00000-3978480550-copy.png"
    ],
    "title": "Pavithra lakshmi post a picture",
    "pg": "3"
  },
  {
    "images": [
      "https://i.ibb.co/mSxWnbq/pavithra-lakshmi-stills-photos-pictures-89.jpg",
      "https://i.ibb.co/2nCy6KX/00005-2161677338-copy.png"
    ],
    "title": "Pavithra lakshmi free photo hosting",
    "pg": "3"
  },
  {
    "images": [
      "https://i.ibb.co/vXL84Md/pavithra-lakshmi-164403833300.jpg",
      "https://i.ibb.co/9hPnvzn/00006-1577508364-copy.png"
    ],
    "title": "Pavithra lakshmi temporary image hosting",
    "pg": "3"
  },
  {
    "images": [
      "https://i.ibb.co/wJBDnKT/pavithra-lakshmi-163876895290.jpg",
      "https://i.ibb.co/74xYMCL/00000-707965322-copy.png"
    ],
    "title": "Pavithra lakshmi",
    "pg": "3"
  },
  {
    "images": [
      "https://i.ibb.co/zh1Qpm5/pavithra-lakshmi-stills-photos-pictures-134.jpg",
      "https://i.ibb.co/hF6ZDgT/00001-1610928587-copy.png"
    ],
    "title": "Pavithra lakshmi",
    "pg": "3"
  },
  {
    "images": [
      "https://i.ibb.co/6RDX2pZ/Janany-Kunaseelan-Age-Family-Husband-Wiki-Biography.jpg",
      "https://i.ibb.co/5Yq8tBG/00002-1882769305-copy.png"
    ],
    "title": "janany kunaseelan quick image upload",
    "pg": "3"
  },
  {
    "images": [
      "https://i.ibb.co/TR0JJt3/janany-kj-janany-kunaseelan-v0-i13xipym26u91.webp",
      "https://i.ibb.co/L8819RQ/00001-3732702144-copy.png"
    ],
    "title": "janany kunaseelan image uploading site",
    "pg": "3"
  },
  {
    "images": [
      "https://i.ibb.co/PZSxMCK/jj3pe1uvv5u91.webp",
      "https://i.ibb.co/K9ThCcJ/00003-3248153342-copy.png"
    ],
    "title": "janany kunaseelan",
    "pg": "4"
  },
  {
    "images": [
      "https://i.ibb.co/4FX3TbK/HD-wallpaper-kritishetty-actress-cute-krithi-krithi-shetty-krithishetty-kriti-kriti-shetty-telugu-ac.jpg",
      "https://i.ibb.co/GHBgPGN/00004-3746918715-copy.png"
    ],
    "title": "Kritishetty picture url",
    "pg": "4"
  },
  {
    "images": [
      "https://i.ibb.co/F6yDFRV/HD-wallpaper-hansika-motwani-actress.jpg",
      "https://i.ibb.co/FDgcR60/00005-951930966-copy.png"
    ],
    "title": "Hansika Motwani",
    "pg": "4"
  },
  {
    "images": [
      "https://i.ibb.co/k4PF0T9/shrutika-arjunhd-wallpapers-desktop-background-android-iphone-1080p-4k-os4co.jpg",
      "https://i.ibb.co/Kzhkm9q/00017-1850001388-copy.png"
    ],
    "title": "shrutika arjun free image hosting sites",
    "pg": "4"
  },
  {
    "images": [
      "https://i.ibb.co/ZXTLTmL/shrutika-arjunhd-wallpapers-desktop-background-android-iphone-1080p-4k-x34cr.jpg",
      "https://i.ibb.co/L16cTnR/00018-4041883173-copy.png"
    ],
    "title": "shrutika arjun",
    "pg": "4"
  },
  {
    "images": [
      "https://i.ibb.co/VBFyT71/shrutika-arjunhd-wallpapers-desktop-background-android-iphone-1080p-4k-3kpsf.jpg",
      "https://i.ibb.co/0V9Rthf/00022-2888312638-copy.png"
    ],
    "title": "shrutika arjun",
    "pg": "4"
  },
  {
    "images": [
      "https://i.ibb.co/8sp4XTY/20230505-145822.jpg",
      "https://i.ibb.co/ZLtZdqq/00002-3212407856-copy.png"
    ],
    "title": "shivani narayanan image upload",
    "pg": "4"
  },
  {
    "images": [
      "https://i.ibb.co/JdHBvZp/photo-2022-01-27-12-09-21-1.jpg",
      "https://i.ibb.co/F6DJyRc/00004-406480607-copy.png"
    ],
    "title": "Ritika Singh image upload",
    "pg": "4"
  },
  {
    "images": [
      "https://i.ibb.co/sFMCPtk/IMG-20230423-151848-808.jpg",
      "https://i.ibb.co/p14PK28/00007-3659402661-copy.png"
    ],
    "title": "samantha ruth prabhu",
    "pg": "4"
  },
  {
    "images": [
      "https://i.ibb.co/7zRVpRz/IMG-20230423-152135-331.jpg",
      "https://i.ibb.co/xm2wWNx/00006-2463934422-copy.png"
    ],
    "title": "samantha ruth prabhu",
    "pg": "4"
  },
  {
    "images": [
      "https://i.ibb.co/0Zh1mtF/00018-3446102341.png",
      "https://i.ibb.co/xXGf648/00008-2272309223-copy.png"
    ],
    "title": "shriya saran",
    "pg": "4"
  },
  {
    "images": [
      "https://i.ibb.co/NnS2q6q/IMG-20230425-170942-407.jpg",
      "https://i.ibb.co/cxpfQQ8/00009-2366094660-copy.png"
    ],
    "title": "tamannaah bhatia",
    "pg": "4"
  },
  {
    "images": [
      "https://i.ibb.co/pxCM51b/IMG-20230425-171107-368.jpg",
      "https://i.ibb.co/WvnwdRD/00010-2249997364-copy.png"
    ],
    "title": "tamannaah bhatia",
    "pg": "4"
  },
  {
    "images": [
      "https://i.ibb.co/HqrZM1r/IMG-20230425-171318-853.jpg",
      "https://i.ibb.co/nbY6G3V/00012-1258399580-copy.png"
    ],
    "title": "tamannaah bhatia",
    "pg": "5"
  },
  {
    "images": [
      "https://i.ibb.co/Mky3tDY/8946-A9-AF-2084-4-E68-BE3-F-723-A3-B72-BC30.jpg",
      "https://i.ibb.co/cNDf65Z/00014-2063014614-copy.png"
    ],
    "title": "",
    "pg": "5"
  },
  {
    "images": [
      "https://i.ibb.co/LpY64Qh/abhirami-venkatachalam-stills-photos-pictures-73.jpg",
      "https://i.ibb.co/3B4PGc0/00006-97200439-copy.png"
    ],
    "title": "ashamed emoticons",
    "pg": "5"
  },
  {
    "images": [
      "https://i.ibb.co/KXDTyD6/abhirami-venkatachalam-stills-photos-pictures-59.jpg",
      "https://i.ibb.co/R4mXyVH/00008-2663269443-copy.png"
    ],
    "title": "abhirami venkatachalam",
    "pg": "5"
  },
  {
    "images": [
      "https://i.ibb.co/P5dycJQ/abhirami-venkatachalam-stills-photos-pictures-43.jpg",
      "https://i.ibb.co/P6M0LwF/00009-669060139-copy.png"
    ],
    "title": "abhirami venkatachalam",
    "pg": "5"
  },
  {
    "images": [
      "https://i.ibb.co/XLHLdZw/peakpx-1.jpg",
      "https://i.ibb.co/mX2VJsn/00022-1563554152-copy.png"
    ],
    "title": "anushka shetty",
    "pg": "5"
  },
  {
    "images": [
      "https://i.ibb.co/wSPvpXy/peakpx.jpg",
      "https://i.ibb.co/CKd9127/00021-411629039-copy.png"
    ],
    "title": "shuti hasan",
    "pg": "5"
  },
  {
    "images": [
      "https://i.ibb.co/nbwg5T8/peakpx-2.jpg",
      "https://i.ibb.co/d6M5LC9/00023-748323071-copy.png"
    ],
    "title": "aishwarya rai my screen size in pixels",
    "pg": "5"
  },
  {
    "images": [
      "https://i.ibb.co/wgQWNNy/peakpx-7.jpg",
      "https://i.ibb.co/xKbWD6v/00028-2524901073-copy.png"
    ],
    "title": "Anagha",
    "pg": "5"
  },
  {
    "images": [
      "https://i.ibb.co/7r7hTpn/peakpx-8.jpg",
      "https://i.ibb.co/C71jmYS/00029-235475294-copy.png"
    ],
    "title": "Anagha my monitor size",
    "pg": "5"
  },
  {
    "images": [
      "https://i.ibb.co/Sfs03RX/peakpx-9.jpg",
      "https://i.ibb.co/FHGj0D6/00030-2176162822-copy.png"
    ],
    "title": "Athulya Ravi",
    "pg": "5"
  },
  {
    "images": [
      "https://i.ibb.co/TM8hdCq/pavithra-janani-5ecbc8a967a2f-1590413481-900.jpg",
      "https://i.ibb.co/W07F4Sg/00006-2402664677-copy.png"
    ],
    "title": "pavithra janani",
    "pg": "6"
  },
  {
    "images": [
      "https://i.ibb.co/xh06w8j/pavithra-janani-5ecbcc0e4ddaa-1590414350-900.jpg",
      "https://i.ibb.co/MVSphkQ/00004-344763760-copy.png"
    ],
    "title": "",
    "pg": "6"
  },
  {
    "images": [
      "https://i.ibb.co/WgwfFxz/ashika-rangnath-20220224-p-2780707663766527958-2-2780707659547107150.jpg",
      "https://i.ibb.co/52d242N/00000-1362118632-copy.png"
    ],
    "title": "ashika rangnath",
    "pg": "6"
  },
  {
    "images": [
      "https://i.ibb.co/2knRHbQ/ashika-rangnath-20230207-p-3032896467925539201-5-3032860727019642539.jpg",
      "https://i.ibb.co/WzYym6T/00001-1810112884-copy.png"
    ],
    "title": "ashika rangnath",
    "pg": "6"
  },
  {
    "images": [
      "https://i.ibb.co/SvZhh1s/9121c76f7856f72137deed894e625836.jpg",
      "https://i.ibb.co/H7Gwp0q/00002-3681038991-copy.png"
    ],
    "title": "ashika rangnath",
    "pg": "6"
  },
  {
    "images": [
      "https://i.ibb.co/2jqF3BT/ashika-rangnath-20221217-p-2995275334145597391-2-2995275329397791145.jpg",
      "https://i.ibb.co/3yBt4LQ/00003-2366811414-copy.png"
    ],
    "title": "ashika rangnath pix image",
    "pg": "6"
  },
  {
    "images": [
      "https://i.ibb.co/cttScvB/ashikarangnatha-fans-20230315-p-3058710230037508884-2-3058710224912040395.jpg",
      "https://i.ibb.co/5GLNgwv/00004-1334246787-copy.png"
    ],
    "title": "ashika rangnath",
    "pg": "6"
  },
  {
    "images": [
      "https://i.ibb.co/NWwnzqj/ashika-rangnath-20230401-p-3071327595073949300-5-3071327590787403847.jpg",
      "https://i.ibb.co/1qzptWn/00005-535638751-copy.png"
    ],
    "title": "ashika rangnath",
    "pg": "6"
  },
  {
    "images": [
      "https://i.ibb.co/vqmCXwN/ashika-rangnath-20230401-p-3071327595073949300-1-3071327590787360646.jpg",
      "https://i.ibb.co/Hzr9NGP/00006-670407675-copy.png"
    ],
    "title": "ashika rangnath",
    "pg": "6"
  },
  {
    "images": [
      "https://i.ibb.co/1fscypc/pavithra-jananihd-wallpapers-desktop-background-android-iphone-1080p-4k-tjvcy.jpg",
      "https://i.ibb.co/z5f8gf3/00023-847121640-copy.png"
    ],
    "title": "pavithra janani",
    "pg": "7"
  },
  {
    "images": [
      "https://i.ibb.co/ch2ZRrW/pavithra-jananihd-wallpapers-desktop-background-android-iphone-1080p-4k-snmvy.jpg",
      "https://i.ibb.co/YDyLXCk/00022-284110610-copy.png"
    ],
    "title": "pavithra janani",
    "pg": "7"
  },
  {
    "images": [
      "https://i.ibb.co/DffBrHG/pavithra-jananihd-wallpapers-desktop-background-android-iphone-1080p-4k-1dph7.jpg",
      "https://i.ibb.co/FxTZJQn/00021-446950526-copy.png"
    ],
    "title": "pavithra janani",
    "pg": "7"
  },
  {
    "images": [
      "https://i.ibb.co/s3FqytG/pavithra-jananihd-wallpapers-desktop-background-android-iphone-1080p-4k-enbxf.jpg",
      "https://i.ibb.co/3RQz63G/00020-2054128977-copy.png"
    ],
    "title": "pavithra janani",
    "pg": "7"
  },
  {
    "images": [
      "https://i.ibb.co/wQQ4637/pavithra-jananihd-wallpapers-desktop-background-android-iphone-1080p-4k-f2wu9.jpg",
      "https://i.ibb.co/X4p6W74/00019-250826048-copy.png"
    ],
    "title": "pavithra janani",
    "pg": "7"
  },
  {
    "images": [
      "https://i.ibb.co/mBPBTyD/pavithra-jananihd-wallpapers-desktop-background-android-iphone-1080p-4k-rhqis.jpg",
      "https://i.ibb.co/NxrT9K3/00017-3191075542-copy.png"
    ],
    "title": "pavithra janani",
    "pg": "7"
  },
  {
    "images": [
      "https://i.ibb.co/860PntJ/peakpx-4.jpg",
      "https://i.ibb.co/X574q44/00046-3572028928-copy.png"
    ],
    "title": "Catherine Tresa",
    "pg": "8"
  },
  {
    "images": [
      "https://i.ibb.co/xY04MdL/peakpx-3.jpg",
      "https://i.ibb.co/FB84nkh/00045-3882922311-copy.png"
    ],
    "title": "Catherine Tresa image upload",
    "pg": "8"
  },
  {
    "images": [
      "https://i.ibb.co/L8xdSFb/peakpx-2.jpg",
      "https://i.ibb.co/6nXZSkQ/00044-2092282468-copy.png"
    ],
    "title": "Catherine Tresa",
    "pg": "8"
  },
  {
    "images": [
      "https://i.ibb.co/Jc9DmLc/peakpx.jpg",
      "https://i.ibb.co/WBkCFtm/00042-1485873736-copy.png"
    ],
    "title": "Catherine Tresa",
    "pg": "8"
  },
  {
    "images": [
      "https://i.ibb.co/VHY0qfW/peakpx-1.jpg",
      "https://i.ibb.co/PMxpgg5/00043-691584923-copy.png"
    ],
    "title": "Catherine Tresa",
    "pg": "8"
  },
  {
    "images": [
      "https://i.ibb.co/1qMx3Wd/pavithra-jananihd-wallpapers-desktop-background-android-iphone-1080p-4k-ktxqp.jpg",
      "https://i.ibb.co/PgpxBvT/00039-3242491850-copy.png"
    ],
    "title": "pavithra janani",
    "pg": "8"
  },
  {
    "images": [
      "https://i.ibb.co/89BgWFM/pavithra-jananihd-wallpapers-desktop-background-android-iphone-1080p-4k-9r0mu.jpg",
      "https://i.ibb.co/p0WGf3p/00040-3371381124-copy.png"
    ],
    "title": "pavithra janani",
    "pg": "8"
  },
  {
    "images": [
      "https://i.ibb.co/Xy9bcMG/pavithra-jananihd-wallpapers-desktop-background-android-iphone-1080p-4k-mgvxz.jpg",
      "https://i.ibb.co/ypfj0by/00041-2761671102-copy.png"
    ],
    "title": "pavithra janani image upload",
    "pg": "8"
  },
  {
    "images": ["https://i.ibb.co/V27L4mz/00038-2233569597-copy.png"],
    "title": "pavithra janani",
    "pg": "8"
  },
  {
    "images": [
      "https://i.ibb.co/Bwj8FZh/2srini-20230418-15.jpg",
      "https://i.ibb.co/BrYtjMt/00000-945699627-copy.png"
    ],
    "title": "srinikha",
    "pg": "8"
  },
  {
    "images": [
      "https://i.ibb.co/8MTcT77/2srini-20230425-1.jpg",
      "https://i.ibb.co/b7RX4g9/00001-254412972-copy.png"
    ],
    "title": "srinikha",
    "pg": "8"
  },
  {
    "images": [
      "https://i.ibb.co/PDDZdbV/2srini-20230317-32.jpg",
      "https://i.ibb.co/0VKxsPn/00002-1208237447-copy.png"
    ],
    "title": "srinikha basho matsuo poems",
    "pg": "8"
  },
  {
    "images": [
      "https://i.ibb.co/3TkT1b2/2srini-20230402-25.jpg",
      "https://i.ibb.co/Kbfm4g9/00004-4007503107-copy.png"
    ],
    "title": "srinikha",
    "pg": "8"
  },
  {
    "images": [
      "https://i.ibb.co/rsJYJ3N/2srini-20230414-11.jpg",
      "https://i.ibb.co/G7kTQLT/00007-1456294660-copy.png"
    ],
    "title": "srinikha",
    "pg": "8"
  },
  {
    "images": [
      "https://i.ibb.co/X8wcZxj/2srini-20230414-9.jpg",
      "https://i.ibb.co/VBwcqcQ/00009-1075219614-copy.png"
    ],
    "title": "srinikha browning home thoughts from abroad",
    "pg": "8"
  },
  {
    "images": [
      "https://i.ibb.co/fpbxqt8/2srini-20230418-3.jpg",
      "https://i.ibb.co/8m2KFL8/00010-2029155074-copy.png"
    ],
    "title": "srinikha",
    "pg": "8"
  },
  {
    "images": [
      "https://i.ibb.co/9b78bFp/2srini-20230418-10.jpg",
      "https://i.ibb.co/5YYK6Zs/00011-2312548586-copy.png"
    ],
    "title": "srinikha she dwelt among the untrodden ways analysis",
    "pg": "8"
  },
  {
    "images": [
      "https://i.ibb.co/HDfg6Qx/peakpx-4.jpg",
      "https://i.ibb.co/yWRpbc0/00018-1835589687-copy.png"
    ],
    "title": "pooja hegde",
    "pg": "9"
  },
  {
    "images": [
      "https://i.ibb.co/gtMYpkm/peakpx-1.jpg",
      "https://i.ibb.co/TKwcc2Y/00016-2854874533-copy.png"
    ],
    "title": "sai pallavi",
    "pg": "9"
  },
  {
    "images": [
      "https://i.ibb.co/rMcnFMD/peakpx-2.jpg",
      "https://i.ibb.co/P4KVw6w/00017-112166041-copy.png"
    ],
    "title": "nithi agarwal",
    "pg": "9"
  },
  {
    "images": [
      "https://i.ibb.co/rc560hg/peakpx-5.jpg",
      "https://i.ibb.co/kQ0CXYj/00019-1455674440-copy.png"
    ],
    "title": "",
    "pg": "9"
  },
  {
    "images": [
      "https://i.ibb.co/QXdc6tf/peakpx-9.jpg",
      "https://i.ibb.co/xhp39QK/00021-772193552-copy.png"
    ],
    "title": "ketika sharma",
    "pg": "9"
  },
  {
    "images": [
      "https://i.ibb.co/zn861sc/peakpx-10.jpg",
      "https://i.ibb.co/W0XJXRw/00022-731263838-copy.png"
    ],
    "title": "ketika sharma",
    "pg": "9"
  },
  {
    "images": [
      "https://i.ibb.co/1R9NPwf/shivangi-beautiful-hd-photos-mobile-wallpapers-hd-androidiphone-1080p-3pqa.jpg",
      "https://i.ibb.co/YkZZWGT/00015-1785717077-copy.png"
    ],
    "title": "cwc sivaangi",
    "pg": "10"
  },
  {
    "images": [
      "https://i.ibb.co/wNMybYw/shivangi-beautiful-hd-photos-mobile-wallpapers-hd-androidiphone-1080p-m5yb.jpg",
      "https://i.ibb.co/kGWRxhT/00016-3270450710-copy.png"
    ],
    "title": "cwc sivaangi",
    "pg": "10"
  },
  {
    "images": [
      "https://i.ibb.co/1KDcBQY/shivani-narayananbigg-boss-latest-hot-hd-photos-wallpapers-1080p-2gvp.jpg",
      "https://i.ibb.co/KGKRHq6/00013-771541355-copy.png"
    ],
    "title": "shivani narayanan",
    "pg": "10"
  },
  {
    "images": [
      "https://i.ibb.co/bsyYnJk/shivani-narayananbigg-boss-latest-hot-hd-photos-wallpapers-1080p-0qgw.jpg",
      "https://i.ibb.co/V2xF4HY/00012-100257864-copy.png"
    ],
    "title": "shivani narayanan best image hosting",
    "pg": "10"
  },
  {
    "images": [
      "https://i.ibb.co/DbzD2S1/shivani-narayananbigg-boss-latest-hot-hd-photos-wallpapers-1080p-oqgw.jpg",
      "https://i.ibb.co/LQK2DWV/00010-32412343-copy.png",
      "https://i.ibb.co/3Rg3P1w/00011-658461825-copy.png"
    ],
    "title": "shivani narayanan",
    "pg": "10"
  },
  {
    "images": [
      "https://i.ibb.co/9vx4Rm0/shivani-narayananbigg-boss-latest-hot-hd-photos-wallpapers-1080p-zh5r.jpg",
      "https://i.ibb.co/fnJjmxG/00005-3394351606-copy.png",
      "https://i.ibb.co/17Vw5p8/00007-880803216-copy.png",
      "https://i.ibb.co/rvzprhb/00009-2426663482-copy.png"
    ],
    "title": "shivani narayanan",
    "pg": "10"
  },
  {
    "images": [
      "https://i.ibb.co/rfDBNqp/shivani-narayananbigg-boss-latest-hot-hd-photos-wallpapers-1080p-yelp.jpg",
      "https://i.ibb.co/fkHs53x/00004-1806911407-copy.png"
    ],
    "title": "shivani narayanan post picture",
    "pg": "10"
  },
  {
    "images": [
      "https://i.ibb.co/Fq4c4Cv/shivani-narayananbigg-boss-latest-hot-hd-photos-wallpapers-1080p-ptvk.jpg",
      "https://i.ibb.co/kQbbdXd/00003-2964357715-copy.png"
    ],
    "title": "shivani narayanan",
    "pg": "10"
  },
  {
    "images": [
      "https://i.ibb.co/FXzbJdN/shivani-narayananbigg-boss-latest-hot-hd-photos-wallpapers-1080p-pkzl.jpg",
      "https://i.ibb.co/52TSTTS/00002-1127970904-copy.png"
    ],
    "title": "shivani narayanan",
    "pg": "10"
  },
  {
    "images": [
      "https://i.ibb.co/1nsStR4/shivani-narayananbigg-boss-latest-hot-hd-photos-wallpapers-1080p-fk8g.jpg",
      "https://i.ibb.co/KVM6dwp/00001-4124225860-copy.png"
    ],
    "title": "shivani narayanan photoupload",
    "pg": "10"
  },
  {
    "images": [
      "https://i.ibb.co/2WBp54w/tabu.jpg",
      "https://i.ibb.co/fdx2qmr/00000-4236208129-copy.png"
    ],
    "title": "tabu",
    "pg": "10"
  },
  {
    "images": [
      "https://i.ibb.co/CBMbh7b/b4eaafa7d39366c18378187113e0d82d.jpg",
      "https://i.ibb.co/q1fL4G5/00002-4257964094-copy.png"
    ],
    "title": "tamanna picture of the picture",
    "pg": "10"
  },
  {
    "images": [
      "https://i.ibb.co/NTBZGFK/andrea-jeremiah-hot-hd-photos-wallpapers-for-mobile-1080p-y1ap.jpg",
      "https://i.ibb.co/n0v075s/00004-335219162-copy.png"
    ],
    "title": "Andrea Jeremiah",
    "pg": "10"
  },
  {
    "images": [
      "https://i.ibb.co/j67pMqf/pressmeet-photos-19441.jpg",
      "https://i.ibb.co/LPR3STL/00005-7227525-copy.png"
    ],
    "title": "Andrea Jeremiah, tamanna",
    "pg": "10"
  },
  {
    "images": [
      "https://i.ibb.co/mz8YzNv/Trisha-Aiswarya.jpg",
      "https://i.ibb.co/XCSSZRn/00001-226320023-copy.png"
    ],
    "title": "trisha krishnan, aishwarya rai",
    "pg": "10"
  },
  {
    "images": [
      "https://i.ibb.co/nwR3FLS/vedika-highres-daggaraga-dooramga54.jpg",
      "https://i.ibb.co/yNwJXHR/00003-1322045610-copy.png"
    ],
    "title": "Vedhika resurrection images free",
    "pg": "11"
  },
  {
    "images": [
      "https://i.ibb.co/hF02DHL/343111617-591224589633828-7554158112085899236-n.jpg",
      "https://i.ibb.co/qsLFw4P/00006-3254124311-copy.png"
    ],
    "title": "Jonita Gandhi",
    "pg": "11"
  },
  {
    "images": [
      "https://i.ibb.co/PZHqwgm/priyanka-arul-mohan-latest-hot-beautiful-hd-photos-1080p-uzyo.jpg",
      "https://i.ibb.co/zbqTg3X/00012-1144052125-copy.png"
    ],
    "title": "Priyanka Mohan",
    "pg": "11"
  },
  {
    "images": [
      "https://i.ibb.co/pQdCyFc/priyanka-arul-mohan-latest-hot-beautiful-hd-photos-1080p-h8lh.jpg",
      "https://i.ibb.co/QkxxJz3/00013-1149308249-copy.png"
    ],
    "title": "Priyanka Mohan",
    "pg": "11"
  },
  {
    "images": [
      "https://i.ibb.co/LJTWXtV/priyanka-arul-mohan-latest-hot-beautiful-hd-photos-1080p-zbbm.jpg",
      "https://i.ibb.co/mt4rWjL/00014-2239440981-copy.png"
    ],
    "title": "Priyanka Mohan",
    "pg": "11"
  },
  {
    "images": [
      "https://i.ibb.co/56LQpyB/priyanka-arul-mohan-latest-hot-beautiful-hd-photos-1080p-zp9g.jpg",
      "https://i.ibb.co/vJk94VB/00015-4073072328-copy.png"
    ],
    "title": "Priyanka Mohan",
    "pg": "11"
  },
  {
    "images": [
      "https://i.ibb.co/wdZFsK7/priyanka-arul-mohan-latest-hot-beautiful-hd-photos-1080p-41jo.jpg",
      "https://i.ibb.co/tzHDQ0h/00016-1830605522-copy.png"
    ],
    "title": "Priyanka Mohan",
    "pg": "11"
  },
  {
    "images": [
      "https://i.ibb.co/MZjtz2G/priyanka-arul-mohan-latest-hot-beautiful-hd-photos-1080p-ybc.jpg",
      "https://i.ibb.co/R6Xx5b2/00017-3454900453-copy.png"
    ],
    "title": "Priyanka Mohan",
    "pg": "11"
  },
  {
    "images": [
      "https://i.ibb.co/fkbnD74/Snapinsta-app-331970885-855401352572628-6638541513192346952-n-1080.jpg",
      "https://i.ibb.co/9rnsH1R/00000-949361796-copy.png"
    ],
    "title": "swathika senthilkumar",
    "pg": "11"
  },
  {
    "images": [
      "https://i.ibb.co/P6GScSM/Snapinsta-app-344571548-621195909565988-348943498619035301-n-1080.jpg",
      "https://i.ibb.co/6sJmjtv/00001-2477018159-copy.png"
    ],
    "title": "swathika senthilkumar",
    "pg": "11"
  },
  {
    "images": [
      "https://i.ibb.co/7VwLCNd/Snapinsta-app-336961495-767285791551233-639886274447309288-n-1080.jpg",
      "https://i.ibb.co/w6FQ17j/00002-3100465610-copy.png"
    ],
    "title": "swathika senthilkumar",
    "pg": "12"
  },
  {
    "images": [
      "https://i.ibb.co/dLTmng1/Snapinsta-app-332386657-1273900560007741-473978814135928544-n-1080.jpg",
      "https://i.ibb.co/kx8WQh9/00003-870538195-copy.png"
    ],
    "title": "swathika senthilkumar first alliance credit union",
    "pg": "12"
  },
  {
    "images": [
      "https://i.ibb.co/BTLWbyc/Snapinsta-app-332419880-147674644810839-7333896442703489454-n-1080.jpg",
      "https://i.ibb.co/BjmnNzf/00004-2206479422-copy.png"
    ],
    "title": "swathika senthilkumar",
    "pg": "12"
  },
  {
    "images": [
      "https://i.ibb.co/mDf1wcg/Snapinsta-app-336505236-522594349824235-2757008964342357318-n-1080.jpg",
      "https://i.ibb.co/DbtjSSZ/00005-2712384978-copy.png"
    ],
    "title": "swathika senthilkumar citymd riverhead",
    "pg": "12"
  },
  {
    "images": [
      "https://i.ibb.co/4W8HdGZ/Snapinsta-app-336502727-1398095570955576-4202564650218306708-n-1080.jpg",
      "https://i.ibb.co/GvfH8b1/00006-1988763863-copy.png"
    ],
    "title": "swathika senthilkumar",
    "pg": "12"
  },
  {
    "images": [
      "https://i.ibb.co/NK91dsr/Snapinsta-app-340992226-1726553617785482-8871401615405240429-n-1080.jpg",
      "https://i.ibb.co/yP6jZ8Y/00009-2475601963-copy.png"
    ],
    "title": "swathika senthilkumar",
    "pg": "12"
  },
  {
    "images": [
      "https://i.ibb.co/tLPbtPS/ammu-abhirami-hot-beautiful-hd-photoshoot-photos-wallpapers-1080p-bcfo.jpg",
      "https://i.ibb.co/nM5VfxW/00011-1090996685-copy.png"
    ],
    "title": "Ammu Abhirami",
    "pg": "12"
  },
  {
    "images": [
      "https://i.ibb.co/9yWvQ9V/ammu-abhirami-hot-beautiful-hd-photoshoot-photos-wallpapers-1080p-1xw5.jpg",
      "https://i.ibb.co/jgpnN64/00013-896206040-copy.png"
    ],
    "title": "Ammu Abhirami",
    "pg": "12"
  },
  {
    "images": [
      "https://i.ibb.co/6sYBPFG/ammu-abhirami-hot-beautiful-hd-photoshoot-photos-wallpapers-1080p-egru.jpg",
      "https://i.ibb.co/VByd6Ph/00014-3101651008-copy.png"
    ],
    "title": "Ammu Abhirami",
    "pg": "12"
  },
  {
    "images": [
      "https://i.ibb.co/YZ4CDTr/ammu-abhirami-hot-beautiful-hd-photoshoot-photos-wallpapers-1080p-1swm.jpg",
      "https://i.ibb.co/cg3pg5n/00015-474685480-copy.png"
    ],
    "title": "Ammu Abhirami",
    "pg": "12"
  },
  {
    "images": [
      "https://i.ibb.co/NWfnSKW/ammu-abhirami-hot-beautiful-hd-photoshoot-photos-wallpapers-1080p-3el0.jpg",
      "https://i.ibb.co/Lvf2sjb/00016-2674435753-copy.png"
    ],
    "title": "Ammu Abhirami",
    "pg": "12"
  },
  {
    "images": [
      "https://i.ibb.co/k53wpLS/ammu-abhirami-hot-beautiful-hd-photoshoot-photos-wallpapers-1080p-b5lz.jpg",
      "https://i.ibb.co/v4r3LZ9/00017-1437641020-copy.png"
    ],
    "title": "Ammu Abhirami minnesota valley credit union",
    "pg": "12"
  },
  {
    "images": [
      "https://i.ibb.co/G7vndJJ/ammu-abhirami-hot-beautiful-hd-photoshoot-photos-wallpapers-1080p-vhf4.jpg",
      "https://i.ibb.co/Yt2SjFt/00019-28273324-copy.png"
    ],
    "title": "Ammu Abhirami",
    "pg": "12"
  },
  {
    "images": [
      "https://i.ibb.co/dgmyFYr/ammu-abhirami-hot-beautiful-hd-photoshoot-photos-wallpapers-1080p-n5wn.jpg",
      "https://i.ibb.co/t3vbjpB/00020-843577478-copy.png"
    ],
    "title": "Ammu Abhirami",
    "pg": "12"
  },
  {
    "images": [
      "https://i.ibb.co/SxKZRYf/ammu-abhirami-hot-beautiful-hd-photoshoot-photos-wallpapers-1080p-a45u.jpg",
      "https://i.ibb.co/4WJJZQ1/00021-1164001109-copy.png"
    ],
    "title": "Ammu Abhirami national philanthropic trust",
    "pg": "12"
  },
  {
    "images": [
      "https://i.ibb.co/C1KbyX2/megha-akash-hd-photos-wallpapers-1080p-sl08.jpg",
      "https://i.ibb.co/7C5t8f4/00007-1366379040-copy.png"
    ],
    "title": "Megha Akash",
    "pg": "12"
  },
  {
    "images": [
      "https://i.ibb.co/C22KJsm/megha-akash-hd-photos-wallpapers-1080p-krkq.jpg",
      "https://i.ibb.co/mzjjhBD/00006-2114885072-copy.png"
    ],
    "title": "Megha Akash",
    "pg": "12"
  },
  {
    "images": [
      "https://i.ibb.co/wL92ybF/megha-akash-hd-photos-wallpapers-1080p-sytk.jpg",
      "https://i.ibb.co/zW31wpF/00005-1104471484-copy.png"
    ],
    "title": "",
    "pg": "12"
  },
  {
    "images": [
      "https://i.ibb.co/chVt83C/megha-akash-hd-photos-wallpapers-1080p-tsrc.jpg",
      "https://i.ibb.co/TmKFMYv/00004-2608809173-copy.png"
    ],
    "title": "Megha Akash",
    "pg": "12"
  },
  {
    "images": [
      "https://i.ibb.co/5kPVwCF/megha-akash-hd-photos-wallpapers-1080p-ure3.jpg",
      "https://i.ibb.co/zRr69tV/00003-2498746483-copy.png"
    ],
    "title": "Megha Akash online dice",
    "pg": "13"
  },
  {
    "images": [
      "https://i.ibb.co/Y8FJjVB/megha-akash-hd-photos-wallpapers-1080p-p66w.jpg",
      "https://i.ibb.co/rtXzTDP/00002-657649364-copy.png"
    ],
    "title": "Megha Akash virtual dice 2",
    "pg": "13"
  },
  {
    "images": [
      "https://i.ibb.co/SBL4C2W/megha-akash-hd-photos-wallpapers-1080p-tlxl.jpg",
      "https://i.ibb.co/9wTv1X2/00001-1001775941-copy.png"
    ],
    "title": "Megha Akash",
    "pg": "13"
  },
  {
    "images": [
      "https://i.ibb.co/6yVkCrL/megha-akash-hd-photos-wallpapers-1080p-hdix.jpg",
      "https://i.ibb.co/FK5jHbr/00000-2147678932-copy.png"
    ],
    "title": "Megha Akash",
    "pg": "13"
  },
  {
    "images": [
      "https://i.ibb.co/3kCrT05/desktop-wallpaper-samantha-akkineni-telugu-actress-navel.jpg",
      "https://i.ibb.co/C0J82jZ/00000-4108138902-copy.png"
    ],
    "title": "samantha",
    "pg": "13"
  },
  {
    "images": [
      "https://i.ibb.co/F7GQrTD/desktop-wallpaper-samantha-akkineni-pushpa-oo-antava-mava.jpg",
      "https://i.ibb.co/cTVbhDZ/00003-1416334788-copy.png"
    ],
    "title": "samantha photoupload",
    "pg": "13"
  },
  {
    "images": [
      "https://i.ibb.co/FJqZy7f/samantha-1.jpg",
      "https://i.ibb.co/BB2DZDW/00005-2400207179-copy.png"
    ],
    "title": "samantha",
    "pg": "13"
  },
  {
    "images": [
      "https://i.ibb.co/34pK5h0/samantha-hot-gallery-2502120939-024.jpg",
      "https://i.ibb.co/znkfGS4/00006-1482952949-copy.png"
    ],
    "title": "samantha upload a photo",
    "pg": "13"
  },
  {
    "images": [
      "https://i.ibb.co/cyrg2vj/samantha-hot-gallery-2502120939-019.jpg",
      "https://i.ibb.co/NLLHBnJ/00007-1079818501-copy.png"
    ],
    "title": "samantha",
    "pg": "13"
  },
  {
    "images": [
      "https://i.ibb.co/Y31jfGR/Samantha-Navel.jpg",
      "https://i.ibb.co/9v7ymbC/00008-178932153-copy.png"
    ],
    "title": "samantha",
    "pg": "13"
  },
  {
    "images": [
      "https://i.ibb.co/YpxNmkb/iswarya-menonhd-wallpapers-desktop-background-android-iphone-1080p-4k-zaimz.jpg",
      "https://i.ibb.co/QXvvtrY/00007-312043796-copy.png"
    ],
    "title": "Iswarya menon",
    "pg": "14"
  },
  {
    "images": [
      "https://i.ibb.co/c12kJD5/iswarya-menonhd-wallpapers-desktop-background-android-iphone-1080p-4k-ty8bc.jpg",
      "https://i.ibb.co/zXvT8xC/00005-3239779257-copy.png"
    ],
    "title": "Iswarya menon pic url maker",
    "pg": "14"
  },
  {
    "images": [
      "https://i.ibb.co/pXbf8zh/iswarya-menonhd-wallpapers-desktop-background-android-iphone-1080p-4k-xzjow.jpg",
      "https://i.ibb.co/8NF4xJ6/00004-1537481247-copy.png"
    ],
    "title": "Iswarya menon",
    "pg": "14"
  },
  {
    "images": [
      "https://i.ibb.co/Lr9MM8m/iswarya-menonhd-wallpapers-desktop-background-android-iphone-1080p-4k-ffznn.jpg",
      "https://i.ibb.co/1sxJPdf/00003-2331125702-copy.png"
    ],
    "title": "Iswarya menon",
    "pg": "14"
  },
  {
    "images": [
      "https://i.ibb.co/NWwNYkQ/iswarya-menonhd-wallpapers-desktop-background-android-iphone-1080p-4k-pc02d.jpg",
      "https://i.ibb.co/sRG83GL/00002-3640595904-copy.png"
    ],
    "title": "Iswarya menon multiple picture upload",
    "pg": "14"
  },
  {
    "images": [
      "https://i.ibb.co/3r4BfW1/iswarya-menonhd-wallpapers-desktop-background-android-iphone-1080p-4k-qscx8.jpg",
      "https://i.ibb.co/Hgq0jMd/00000-1218202139-copy.png"
    ],
    "title": "Iswarya menon upload photo on net",
    "pg": "14"
  },
  {
    "images": [
      "https://i.ibb.co/W6SW0CS/iswarya-menonhd-wallpapers-desktop-background-android-iphone-1080p-4k-vywmf.jpg",
      "https://i.ibb.co/XZmSzp8/00001-3628678889-copy.png"
    ],
    "title": "Iswarya menon",
    "pg": "14"
  },
  {
    "images": [
      "https://i.ibb.co/jhWPVNn/indhuja-ravichandranhd-wallpapers-desktop-background-android-iphone-1080p-4k-wep1v.jpg",
      "https://i.ibb.co/vcy6M9G/00008-225707627-copy.png"
    ],
    "title": "Indhuja Ravichandran",
    "pg": "14"
  },
  {
    "images": [
      "https://i.ibb.co/pLs4X6w/indhuja-ravichandranhd-wallpapers-desktop-background-android-iphone-1080p-4k-6v5ce.jpg",
      "https://i.ibb.co/hsytzZ0/00009-3013236071-copy.png"
    ],
    "title": "Indhuja Ravichandran",
    "pg": "14"
  },
  {
    "images": [
      "https://i.ibb.co/LvLHS7X/indhuja-ravichandranhd-wallpapers-desktop-background-android-iphone-1080p-4k-7ddcw.jpg",
      "https://i.ibb.co/cyXPZFB/00010-2693433592-copy.png"
    ],
    "title": "Indhuja Ravichandran",
    "pg": "14"
  },
  {
    "images": [
      "https://i.ibb.co/hY6NKXq/indhuja-ravichandran-super-duper-movie-launch-41.jpg",
      "https://i.ibb.co/g987Lv3/00011-2191636201-copy.png"
    ],
    "title": "Indhuja Ravichandran",
    "pg": "14"
  },
  {
    "images": [
      "https://i.ibb.co/jDJS0Dg/indhuja-ravichandran-super-duper-movie-launch-22.jpg",
      "https://i.ibb.co/MB4kBPK/00012-3672401232-copy.png"
    ],
    "title": "Indhuja Ravichandran modistes crossword",
    "pg": "14"
  },
  {
    "images": [
      "https://i.ibb.co/LzJ125b/indhuja-ravichandran-super-duper-movie-launch-1.jpg",
      "https://i.ibb.co/sQqQPpX/00013-1485258558-copy.png"
    ],
    "title": "Indhuja Ravichandran",
    "pg": "14"
  },
  {
    "images": [
      "https://i.ibb.co/phzt8v0/indhuja-ravichandranhd-wallpapers-desktop-background-android-iphone-1080p-4k-les3y.jpg",
      "https://i.ibb.co/1vxphrt/00017-2855097186-copy.png"
    ],
    "title": "Indhuja Ravichandran",
    "pg": "14"
  },
  {
    "images": [
      "https://i.ibb.co/fHFc5KH/nazriya-nazimhd-wallpapers-desktop-background-android-iphone-1080p-4k-3fjc3.jpg",
      "https://i.ibb.co/TMZLcRh/00027-4203904996-copy.png"
    ],
    "title": "Nazriya Nazim maurice chevalier musical crossword",
    "pg": "14"
  },
  {
    "images": [
      "https://i.ibb.co/LY072n0/nazriya-nazimhd-wallpapers-desktop-background-android-iphone-1080p-4k-bsxi1.jpg",
      "https://i.ibb.co/dQ3cLnS/00026-3419693168-copy.png"
    ],
    "title": "Nazriya Nazim",
    "pg": "14"
  },
  {
    "images": [
      "https://i.ibb.co/w0mbS6P/nazriya-nazimhd-wallpapers-desktop-background-android-iphone-1080p-4k-jpsdy.jpg",
      "https://i.ibb.co/HDD4d10/00025-2955092631-copy.png"
    ],
    "title": "Nazriya Nazim",
    "pg": "15"
  },
  {
    "images": [
      "https://i.ibb.co/GFjJbVF/nazriya-nazimhd-wallpapers-desktop-background-android-iphone-1080p-4k-iva4u.jpg",
      "https://i.ibb.co/wQm9b1M/00024-1881187303-copy.png"
    ],
    "title": "Nazriya Nazim",
    "pg": "15"
  },
  {
    "images": [
      "https://i.ibb.co/VwrFWzk/nazriya-nazimhd-wallpapers-desktop-background-android-iphone-1080p-4k-uzy7h.jpg",
      "https://i.ibb.co/SccS22K/00023-3620432439-copy.png"
    ],
    "title": "Nazriya Nazim",
    "pg": "15"
  },
  {
    "images": [
      "https://i.ibb.co/TDX8c7Q/nazriya-nazimhd-wallpapers-desktop-background-android-iphone-1080p-4k-yj9ht.jpg",
      "https://i.ibb.co/f834fVr/00020-2845381128-copy.png"
    ],
    "title": "Nazriya Nazim",
    "pg": "15"
  },
  {
    "images": [
      "https://i.ibb.co/bHdr68J/nazriya-nazimhd-wallpapers-desktop-background-android-iphone-1080p-4k-ewfqy.jpg",
      "https://i.ibb.co/W2Vt4wq/00019-3222990422-copy.png"
    ],
    "title": "Nazriya Nazim",
    "pg": "15"
  },
  {
    "images": [
      "https://i.ibb.co/68fs6LG/nazriya-nazimhd-wallpapers-desktop-background-android-iphone-1080p-4k-yit55.jpg",
      "https://i.ibb.co/tJLFFD4/00018-13156491-copy.png"
    ],
    "title": "Nazriya Nazim 2013 tonto portrayer crossword clue",
    "pg": "15"
  },
  {
    "images": [
      "https://i.ibb.co/bb7ZZjv/gayathri-yuvraaj-20230510-12.jpg",
      "https://i.ibb.co/NrQr76x/00035-1684587638-copy.png"
    ],
    "title": "Gayathri Yuvraaj",
    "pg": "15"
  },
  {
    "images": [
      "https://i.ibb.co/ssVKj2G/gayathri-yuvraaj-20230510-24.jpg",
      "https://i.ibb.co/TMnBsbh/00034-669605456-copy.png"
    ],
    "title": "Gayathri Yuvraaj",
    "pg": "16"
  },
  {
    "images": [
      "https://i.ibb.co/ZS00wrd/gayathri-yuvraaj-20230510-5.jpg",
      "https://i.ibb.co/p3zvLKT/00037-2840373961-copy.png"
    ],
    "title": "Gayathri Yuvraaj pic host",
    "pg": "16"
  },
  {
    "images": [
      "https://i.ibb.co/Dknd1mV/gayathri-yuvraaj-20230510-23-1.jpg",
      "https://i.ibb.co/R0tPtgw/00033-1932590245-copy.png"
    ],
    "title": "Gayathri Yuvraaj",
    "pg": "16"
  },
  {
    "images": [
      "https://i.ibb.co/4N3tnjT/gayathri-yuvraaj-20230510-25.jpg",
      "https://i.ibb.co/qBxkS14/00032-685309079-copy.png"
    ],
    "title": "Gayathri Yuvraaj",
    "pg": "16"
  },
  {
    "images": [
      "https://i.ibb.co/4Tk05yr/gayathri-yuvraaj-20230510-28.jpg",
      "https://i.ibb.co/y56hmDw/00031-2561941042-copy.png"
    ],
    "title": "Gayathri Yuvraaj",
    "pg": "16"
  },
  {
    "images": [
      "https://i.ibb.co/r6pJKFq/gayathri-yuvraaj-20230510-34.jpg",
      "https://i.ibb.co/L9mCy6P/00030-2786899910-copy.png"
    ],
    "title": "Gayathri Yuvraaj",
    "pg": "16"
  },
  {
    "images": [
      "https://i.ibb.co/6PK4y8g/gayathri-yuvraaj-20230510-36.jpg",
      "https://i.ibb.co/BNKFXGZ/00029-2904684955-copy.png"
    ],
    "title": "Gayathri Yuvraaj",
    "pg": "16"
  },
  {
    "images": [
      "https://i.ibb.co/Y7JKShs/gayathri-yuvraaj-20230510-38.jpg",
      "https://i.ibb.co/6g3bSxr/00028-1701895270-copy.png"
    ],
    "title": "Gayathri Yuvraaj",
    "pg": "16"
  },
  {
    "images": [
      "https://i.ibb.co/Bg97p9M/gayathri-yuvraaj-20230510-41.jpg",
      "https://i.ibb.co/PGG1fK4/00027-1761378246-copy.png"
    ],
    "title": "Gayathri Yuvraaj",
    "pg": "16"
  },
  {
    "images": [
      "https://i.ibb.co/Bg6gqvr/gayathri-yuvraaj-20230510-43.jpg",
      "https://i.ibb.co/JBWZ6dx/00026-1842290722-copy.png"
    ],
    "title": "Gayathri Yuvraaj",
    "pg": "16"
  },
  {
    "images": [
      "https://i.ibb.co/ZHdqSth/gayathri-yuvraaj-20230510-46.jpg",
      "https://i.ibb.co/h80TJ2p/00025-3214648852-copy.png"
    ],
    "title": "Gayathri Yuvraaj",
    "pg": "16"
  },
  {
    "images": [
      "https://i.ibb.co/RBCh1GJ/gayathri-yuvraaj-20230510-50.jpg",
      "https://i.ibb.co/hCs7gyY/00024-2923449048-copy.png"
    ],
    "title": "Gayathri Yuvraaj",
    "pg": "16"
  },
  {
    "images": [
      "https://i.ibb.co/b16RhtM/gayathri-yuvraaj-20230510-48.jpg",
      "https://i.ibb.co/MM9RQBd/00022-4078624936-copy.png"
    ],
    "title": "Gayathri Yuvraaj",
    "pg": "16"
  },
  {
    "images": [
      "https://i.ibb.co/0XT8Q6d/gayathri-yuvraaj-20230510-57.jpg",
      "https://i.ibb.co/DPJZZg0/00021-3788226693-copy.png"
    ],
    "title": "Gayathri Yuvraaj",
    "pg": "16"
  },
  {
    "images": [
      "https://i.ibb.co/f0CxQ9b/gayathri-yuvraaj-20230510-58.jpg",
      "https://i.ibb.co/6s5J770/00020-529875633-copy.png"
    ],
    "title": "Gayathri Yuvraaj",
    "pg": "16"
  },
  {
    "images": [
      "https://i.ibb.co/q5f8wMR/gayathri-yuvraaj-20230402-40.jpg",
      "https://i.ibb.co/NCnZnW1/00019-3836811100-copy.png"
    ],
    "title": "Gayathri Yuvraaj free photo upload",
    "pg": "16"
  },
  {
    "images": [
      "https://i.ibb.co/DVzr6FY/gayathri-yuvraaj-20230402-42.jpg",
      "https://i.ibb.co/fntkY3X/00018-688774745-copy.png"
    ],
    "title": "Gayathri Yuvraaj image hoster",
    "pg": "16"
  },
  {
    "images": [
      "https://i.ibb.co/5hhgDRg/gayathri-yuvraaj-20230330-22.jpg",
      "https://i.ibb.co/vV3PTrT/00017-4145061756-copy.png"
    ],
    "title": "Gayathri Yuvraaj",
    "pg": "16"
  },
  {
    "images": [
      "https://i.ibb.co/x7WLmw8/gayathri-yuvraaj-20230329-10.jpg",
      "https://i.ibb.co/JmVtgjH/00016-2657757064-copy.png"
    ],
    "title": "Gayathri Yuvraaj",
    "pg": "16"
  },
  {
    "images": [
      "https://i.ibb.co/sFLbXKv/gayathri-yuvraaj-20230329-8.jpg",
      "https://i.ibb.co/yfHbcKW/00014-3974878464-copy.png"
    ],
    "title": "Gayathri Yuvraaj",
    "pg": "16"
  },
  {
    "images": [
      "https://i.ibb.co/51W8Ntj/gayathri-yuvraaj-20230323-4.jpg",
      "https://i.ibb.co/brPwdDS/00013-3682168767-copy.png"
    ],
    "title": "Gayathri Yuvraaj",
    "pg": "17"
  },
  {
    "images": [
      "https://i.ibb.co/4pfQPWz/gayathri-yuvraaj-20230510-1-1.jpg",
      "https://i.ibb.co/L52WHbg/00012-2598312279-copy.png"
    ],
    "title": "Gayathri Yuvraaj",
    "pg": "17"
  },
  {
    "images": [
      "https://i.ibb.co/Dknd1mV/gayathri-yuvraaj-20230510-23-1.jpg",
      "https://i.ibb.co/cyFJQBC/00011-17013129-copy.png"
    ],
    "title": "Gayathri Yuvraaj",
    "pg": "17"
  },
  {
    "images": [
      "https://i.ibb.co/QFs0MSt/gayathri-yuvraaj-20230322-2.jpg",
      "https://i.ibb.co/Nr5YCVV/00010-2116204629-copy.png"
    ],
    "title": "Gayathri Yuvraaj upload pictures online",
    "pg": "17"
  },
  {
    "images": [
      "https://i.ibb.co/4MxBKRk/gayathri-yuvraaj-20230322-1.jpg",
      "https://i.ibb.co/8rvrncZ/00009-1831931700-copy.png"
    ],
    "title": "Gayathri Yuvraaj",
    "pg": "17"
  },
  {
    "images": [
      "https://i.ibb.co/X5b5tCG/rachitha-mahalakshmihd-wallpapers-desktop-background-android-iphone-1080p-4k-ocihc.jpg",
      "https://i.ibb.co/Byz1Ms9/00006-384114295-copy.png"
    ],
    "title": "Rachitha Mahalakshmi",
    "pg": "17"
  },
  {
    "images": [
      "https://i.ibb.co/SyHPfZS/rachitha-mahalakshmihd-wallpapers-desktop-background-android-iphone-1080p-4k-5vocj.jpg",
      "https://i.ibb.co/HBNCzhh/00005-1246571336-copy.png"
    ],
    "title": "Rachitha Mahalakshmi",
    "pg": "17"
  },
  {
    "images": [
      "https://i.ibb.co/k2rrrfb/rachitha-mahalakshmihd-wallpapers-desktop-background-android-iphone-1080p-4k-grrii-1.webp",
      "https://i.ibb.co/dJkZmBH/00004-3543751701-copy.png"
    ],
    "title": "Rachitha Mahalakshmi",
    "pg": "17"
  },
  {
    "images": [
      "https://i.ibb.co/J7MdqhR/rachitha-mahalakshmihd-wallpapers-desktop-background-android-iphone-1080p-4k-72i6q-1.webp",
      "https://i.ibb.co/f0tMmjP/00003-2757653918-copy.png"
    ],
    "title": "Rachitha Mahalakshmi online upload image",
    "pg": "17"
  },
  {
    "images": [
      "https://i.ibb.co/gMVrKyq/rachitha-mahalakshmihd-wallpapers-desktop-background-android-iphone-1080p-4k-lh9pq.jpg",
      "https://i.ibb.co/j8rw9NG/00002-4015196101-copy.png"
    ],
    "title": "Rachitha Mahalakshmi",
    "pg": "17"
  },
  {
    "images": [
      "https://i.ibb.co/NYzLgfg/rashmika-mandannahd-wallpapers-desktop-background-android-iphone-1080p-4k-fqhom.jpg",
      "https://i.ibb.co/Dz4hxM1/00007-2270574258-copy.png"
    ],
    "title": "Rashmika Mandanna",
    "pg": "17"
  },
  {
    "images": [
      "https://i.ibb.co/J2pS6cY/rashmika-mandanna-sulthan-pre-release43.jpg",
      "https://i.ibb.co/rbnfvhQ/00004-225385577-copy.png"
    ],
    "title": "Rashmika Mandanna",
    "pg": "17"
  },
  {
    "images": [
      "https://i.ibb.co/PrYKLdY/rashmika-mandannahd-wallpapers-desktop-background-android-iphone-1080p-4k-gqico.jpg",
      "https://i.ibb.co/Fm5jKF6/00003-2855503247-copy.png"
    ],
    "title": "Rashmika Mandanna",
    "pg": "17"
  },
  {
    "images": [
      "https://i.ibb.co/XJq6RXF/rashmika-mandannahd-wallpapers-desktop-background-android-iphone-1080p-4k-nwonb.jpg",
      "https://i.ibb.co/C6GWg5M/00002-2772134491-copy.png"
    ],
    "title": "Rashmika Mandanna",
    "pg": "18"
  },
  {
    "images": [
      "https://i.ibb.co/tLyzQPd/rashmika-mandannahd-wallpapers-desktop-background-android-iphone-1080p-4k-saihy.jpg",
      "https://i.ibb.co/ZGpy5JS/00000-3106832747-copy.png"
    ],
    "title": "Rashmika Mandanna",
    "pg": "18"
  },
  {
    "images": [
      "https://i.ibb.co/z5TV5vw/anu-emmanuel-snap-fitness-gym1.jpg",
      "https://i.ibb.co/5TGGPmR/00015-902672248-copy.png"
    ],
    "title": "Anu Emmanuel",
    "pg": "18"
  },
  {
    "images": [
      "https://i.ibb.co/ftDkY2J/anu-emmanuel-urvasivo-rakshasivo-pre-release1.jpg",
      "https://i.ibb.co/k2mGPxt/00009-1889769833-copy.png"
    ],
    "title": "Anu Emmanuel",
    "pg": "18"
  },
  {
    "images": [
      "https://i.ibb.co/gVLQ5Zw/anu-emmanuel-maha-samudram-pre-release4.jpg",
      "https://i.ibb.co/y0vwxzk/00011-2640714344-copy.png"
    ],
    "title": "Anu Emmanuel",
    "pg": "18"
  },
  {
    "images": [
      "https://i.ibb.co/CVtv81Q/anu-emmanuel-maha-samudram-pre-release16.jpg",
      "https://i.ibb.co/xsQKN17/00012-1498176906-copy.png"
    ],
    "title": "Anu Emmanuel images upload",
    "pg": "18"
  },
  {
    "images": [
      "https://i.ibb.co/TYndDKC/anu-emmanuel-in-saree15.jpg",
      "https://i.ibb.co/W69gTH1/00013-2532866760-copy.png"
    ],
    "title": "Anu Emmanuel",
    "pg": "18"
  },
  {
    "images": [
      "https://i.ibb.co/WV7mqHm/anu-emmanuel-naa-peru-surya6.jpg",
      "https://i.ibb.co/rk9gWpZ/00014-3568483085-copy.png"
    ],
    "title": "Anu Emmanuel gif upload",
    "pg": "18"
  },
  {
    "images": [
      "https://i.ibb.co/5YhxtWF/anu-emmanuel-klm-launch4.jpg",
      "https://i.ibb.co/7KywSkW/00018-2978977720-copy.png"
    ],
    "title": "Anu Emmanuel",
    "pg": "18"
  },
  {
    "images": [
      "https://i.ibb.co/zFFVbB2/keerthy-suresh-stills-photos-pictures-749.jpg",
      "https://i.ibb.co/hMzwznD/keerthy-suresh-stills-photos-pictures-673.jpg",
      "https://i.ibb.co/wBtdd5v/keerthy-suresh-stills-photos-pictures-418.jpg",
      "https://i.ibb.co/4Yr3tsL/keerthy-suresh-stills-photos-pictures-415.jpg",
      "https://i.ibb.co/M2ggXYn/keerthy-suresh-stills-photos-pictures-413.jpg",
      "https://i.ibb.co/Vjxfm0n/keerthy-suresh-stills-photos-pictures-285.jpg",
      "https://i.ibb.co/c87cT6G/keerthy-suresh-stills-photos-pictures-284.jpg",
      "https://i.ibb.co/q0ZLFJ0/Keerthy-Suresh-Stills-in-Traditional-Saree-for-Onam-Celebrations-Links-Ind.jpg",
      "https://i.ibb.co/GsPKr7d/Keerthi-Suresh-at-Rajini-Murugan-Audio-Launch-12.jpg",
      "https://i.ibb.co/F6vk9ws/Manju-Warrier-in-Odiyan-5.jpg",
      "https://i.ibb.co/DzhTVGW/Manju-Warrier-in-Odiyan-4.jpg",
      "https://i.ibb.co/HGgRfLQ/Manju-Warrier-in-Odiyan-3.jpg"
    ],
    "title": "Bro Please Do bro... pls pls pls...",
    "pg": "18"
  },
  {
    "images": [
      "https://i.ibb.co/YbtcgHv/keerthy-suresh-stills-photos-pictures-749.jpg",
      "https://i.ibb.co/9YfcXHX/00019-995888824-copy.png"
    ],
    "title": "",
    "pg": "18"
  },
  {
    "images": [
      "https://i.ibb.co/Wz1ncCm/keerthy-suresh-stills-photos-pictures-284.jpg",
      "https://i.ibb.co/Tqc8mJM/00018-277692048-copy.png"
    ],
    "title": "keerthy suresh",
    "pg": "18"
  },
  {
    "images": [
      "https://i.ibb.co/92mSnSd/anju-kurian-latest-photos-nov22-20211.jpg",
      "https://i.ibb.co/BG8c2mG/00020-3459724092-copy.png"
    ],
    "title": "anju kurian",
    "pg": "18"
  },
  {
    "images": [
      "https://i.ibb.co/2Z23Ntt/anju-kurian-latest-photos-nov22-20219.jpg",
      "https://i.ibb.co/cxM4Vvn/00021-3246335489-copy.png"
    ],
    "title": "anju kurian",
    "pg": "19"
  },
  {
    "images": [
      "https://i.ibb.co/bvfX98P/anju-kurian-siima20211.jpg",
      "https://i.ibb.co/4MRSp0N/00022-4033644215-copy.png"
    ],
    "title": "anju kurian photo upload website",
    "pg": "19"
  },
  {
    "images": [
      "https://i.ibb.co/LZ3vKrw/anju-kurian-siima2021-day21.jpg",
      "https://i.ibb.co/VmZ5y05/00025-1355072599-copy.png"
    ],
    "title": "anju kurian",
    "pg": "19"
  },
  {
    "images": [
      "https://i.ibb.co/rMLn01p/anju-kurian-siima2021-day211.jpg",
      "https://i.ibb.co/zXxygFK/00024-881907415-copy.png"
    ],
    "title": "anju kurian",
    "pg": "19"
  },
  {
    "images": [
      "https://i.ibb.co/sR8Tgv8/IMG-0429.jpg",
      "https://i.ibb.co/kqBb1gS/00026-4101879765-copy.png"
    ],
    "title": "Rashmika mandana free photo upload",
    "pg": "19"
  },
  {
    "images": [
      "https://i.ibb.co/vQ2jkkw/output-8.png",
      "https://i.ibb.co/8KtmZmY/00027-142886372-copy.png"
    ],
    "title": "varsha DSouza",
    "pg": "19"
  },
  {
    "images": [
      "https://i.ibb.co/rt9tVjK/output-5.png",
      "https://i.ibb.co/Tgk7kGY/00028-2135401240-copy.png"
    ],
    "title": "varsha DSouza",
    "pg": "19"
  },
  {
    "images": [
      "https://i.ibb.co/Z8FHF9Q/output-7.png",
      "https://i.ibb.co/KFCTGzK/00029-1317680883-copy.png"
    ],
    "title": "varsha DSouza",
    "pg": "19"
  },
  {
    "images": [
      "https://i.ibb.co/yS2FCNr/output.png",
      "https://i.ibb.co/F4vd2Sz/00030-1120829992-copy.png"
    ],
    "title": "varsha DSouza",
    "pg": "19"
  },
  {
    "images": [
      "https://i.ibb.co/nmw7Wng/output-6.png",
      "https://i.ibb.co/hVTcKHc/00031-225012046-copy.png"
    ],
    "title": "varsha DSouza",
    "pg": "19"
  },
  {
    "images": [
      "https://i.ibb.co/kyhzYsK/output-2.png",
      "https://i.ibb.co/pQk51LR/00032-3343840826-copy.png"
    ],
    "title": "varsha DSouza upload gif online",
    "pg": "19"
  },
  {
    "images": [
      "https://i.ibb.co/ncM8GW3/Manju-Warrier-in-Odiyan-5.jpg",
      "https://i.ibb.co/89gqTHw/Manju-Warrier-in-Odiyan-4.jpg",
      "https://i.ibb.co/k56h7Jq/IMG-20230129-214214-902.jpg",
      "https://i.ibb.co/k0cWVqG/download-37.jpg",
      "https://i.ibb.co/9hsKwX8/download-36.jpg",
      "https://i.ibb.co/cLgRj1z/download-24.jpg",
      "https://i.ibb.co/F0Cc1pr/download-15.jpg",
      "https://i.ibb.co/KKJ1qT9/download-14.jpg",
      "https://i.ibb.co/yFN580T/download-9.jpg",
      "https://i.ibb.co/hR1GTKg/download-4.jpg",
      "https://i.ibb.co/fvPMHZH/Asuran-Actress-Manju-Warrier-2019-Pretty-Unseen-Stills-Gethu-Cinema.jpg",
      "https://i.ibb.co/0hf1cg6/308350847-489289812813020-2047479056712068696-n.jpg"
    ],
    "title": "",
    "pg": "19"
  },
  {
    "images": [
      "https://i.ibb.co/R7hZWH3/sneha720.jpg",
      "https://i.ibb.co/R3SNhqt/00003-1185162366-copy.png"
    ],
    "title": "sneha",
    "pg": "20"
  },
  {
    "images": [
      "https://i.ibb.co/xjPfm2G/desktop-wallpaper-priya-anand-latest-hot-from-tamil-movie-priya-anand-iphone.jpg",
      "https://i.ibb.co/dmPjftt/00004-4157527658-copy.png"
    ],
    "title": "priya anand",
    "pg": "20"
  },
  {
    "images": [
      "https://i.ibb.co/7Vh0DJp/desktop-wallpaper-priya-anand-tamil-actress.jpg",
      "https://i.ibb.co/ccjkbzQ/00005-17936903-copy.png"
    ],
    "title": "priya anand",
    "pg": "20"
  },
  {
    "images": [
      "https://i.ibb.co/Svf1gBC/desktop-wallpaper-priya-anand-tamil-actress-navel-show.jpg",
      "https://i.ibb.co/fktnLb3/00007-1869641273-copy.png"
    ],
    "title": "priya anand",
    "pg": "20"
  },
  {
    "images": [
      "https://i.ibb.co/23GpLLx/desktop-wallpaper-celebrity-priya-anand-priya-anand-phone.jpg",
      "https://i.ibb.co/gvxTBMt/00006-1915833531-copy.png"
    ],
    "title": "priya anand",
    "pg": "20"
  },
  {
    "images": [
      "https://i.ibb.co/7RRGvbf/sneha-vvr-pre-release5.jpg",
      "https://i.ibb.co/Jzf6LxQ/00002-3079539500-copy.png"
    ],
    "title": "sneha",
    "pg": "20"
  },
  {
    "images": [
      "https://i.ibb.co/mvM131Y/rajakota-rahasyam-heroine-sneha9.jpg",
      "https://i.ibb.co/JFkV95v/00001-1050092571-copy.png"
    ],
    "title": "sneha",
    "pg": "20"
  },
  {
    "images": [
      "https://i.ibb.co/PxkrcXD/rajakota-rahasyam-heroine-sneha13.jpg",
      "https://i.ibb.co/c6rShW9/00000-527400154-copy.png"
    ],
    "title": "sneha",
    "pg": "20"
  },
  {
    "images": [
      "https://i.ibb.co/717X1z2/desktop-wallpaper-tabu-bollywood-actress-navel.jpg",
      "https://i.ibb.co/Ht1yC4S/00008-678330367-copy.png"
    ],
    "title": "tabu",
    "pg": "20"
  },
  {
    "images": [
      "https://i.ibb.co/THH2Ywk/desktop-wallpaper-tabu-bollywood-actress-navel-1.jpg",
      "https://i.ibb.co/B2Hq9kT/00009-876112620-copy.png"
    ],
    "title": "tabu",
    "pg": "20"
  },
  {
    "images": [
      "https://i.ibb.co/3rj4wNJ/Devayani-8118.jpg",
      "https://i.ibb.co/9Wb4ZDq/00045-592894529-copy.png"
    ],
    "title": "devayani",
    "pg": "20"
  },
  {
    "images": [
      "https://i.ibb.co/hKQZpzX/8325735.jpg",
      "https://i.ibb.co/bXyCpR8/00046-488559002-copy.png"
    ],
    "title": "devayani",
    "pg": "20"
  },
  {
    "images": [
      "https://i.ibb.co/59ZYmKW/1684003639625.jpg",
      "https://i.ibb.co/V2Mpmg2/00048-2477463069-copy.png",
      "https://i.ibb.co/FbZQmBb/00047-1480349685-copy.png"
    ],
    "title": "malavika mohanan",
    "pg": "20"
  },
  {
    "images": [
      "https://i.ibb.co/L0QfJbN/IMG-20230513-222805.jpg",
      "https://i.ibb.co/PxS4LCC/00025-622339882-copy.png"
    ],
    "title": "nivetha thomas",
    "pg": "20"
  },
  {
    "images": [
      "https://i.ibb.co/8PJ6QVq/IMG-20230513-222904.jpg",
      "https://i.ibb.co/0V0HKd3/00026-4241087958-copy.png"
    ],
    "title": "Manjima Mohan my monitor resolution",
    "pg": "20"
  },
  {
    "images": [
      "https://i.ibb.co/S60vGVX/IMG-20230513-222934.jpg",
      "https://i.ibb.co/NTGVhD8/00028-37175271-copy.png"
    ],
    "title": "Priyanka Mohan",
    "pg": "20"
  },
  {
    "images": [
      "https://i.ibb.co/7tQCXd2/IMG-20230513-222540.jpg",
      "https://i.ibb.co/TmV3sxG/00029-3036768005-copy.png"
    ],
    "title": "anupama parameswaran",
    "pg": "20"
  },
  {
    "images": [
      "https://i.ibb.co/KzdSr07/IMG-20230513-222749.jpg",
      "https://i.ibb.co/92frHCW/00030-140397656-copy.png"
    ],
    "title": "nivetha thomas lackawanna railroad crossword",
    "pg": "21"
  },
  {
    "images": [
      "https://i.ibb.co/MSpWb3V/IMG-20230513-222640.jpg",
      "https://i.ibb.co/TbtFtB5/00034-843975140-copy.png"
    ],
    "title": "anupama parameswaran singer laine et al crossword",
    "pg": "21"
  },
  {
    "images": [
      "https://i.ibb.co/WPjZ6yJ/HD-wallpaper-regina-cassendra-actress-navel-south-indian-sree-telugu-traditional.jpg",
      "https://i.ibb.co/jVhZxZM/00035-3812738815-copy.png"
    ],
    "title": "ragina",
    "pg": "21"
  },
  {
    "images": [
      "https://i.ibb.co/Qn5FxdB/IMG-20230513-222614.jpg",
      "https://i.ibb.co/qnbrWTq/00036-1961859837-copy.png"
    ],
    "title": "anupama parameswaran",
    "pg": "21"
  },
  {
    "images": [
      "https://i.ibb.co/s9HCdpc/HD-wallpaper-nivetha-thomas-actress-malayalam-actress-nivethathomas-telugu-actress-telugu-movie.jpg",
      "https://i.ibb.co/g3BrcKh/00037-2709295036-copy.png"
    ],
    "title": "nivetha thomas worked with rattan crossword",
    "pg": "21"
  },
  {
    "images": [
      "https://i.ibb.co/bv0yhLj/HD-wallpaper-manjima-mohan-actress-girl.jpg",
      "https://i.ibb.co/fqXM90z/00039-4160792540-copy.png"
    ],
    "title": "Manjima Mohan",
    "pg": "21"
  },
  {
    "images": [
      "https://i.ibb.co/9T0tpT9/HD-wallpaper-manjima-mohan-actress-tamil.jpg",
      "https://i.ibb.co/Y7rLn78/00040-2693541149-copy.png"
    ],
    "title": "Manjima Mohan",
    "pg": "21"
  },
  {
    "images": [
      "https://i.ibb.co/j5j42gN/15u-PZSsn5u-Aw96-N7-U6-Yad4-ALJZC8h-Boy7cg-TJhby-HOn-b-Puo-GCUSCAVso-Bvg-fs.jpg",
      "https://i.ibb.co/gdfb9wz/00041-2978973386-copy.png"
    ],
    "title": "gayathri yuvaraj",
    "pg": "21"
  },
  {
    "images": [
      "https://i.ibb.co/tmK2FYD/L7eafucv3-Av-Mg-FYn-Djt-BCkk-JZg-H4-Mo-DRMPca-Uii-Lc-Ddzv-Td-PIxm-Uxa3rm-Ycv-RM.jpg",
      "https://i.ibb.co/syggjTx/00042-305757706-copy.png"
    ],
    "title": "gayathri yuvaraj",
    "pg": "21"
  },
  {
    "images": [
      "https://i.ibb.co/ZK1CvNS/8325719.jpg",
      "https://i.ibb.co/6ssvKVq/00043-1504941797-copy.png"
    ],
    "title": "devayani",
    "pg": "21"
  },
  {
    "images": [
      "https://i.ibb.co/8swM1Tj/d7.jpg",
      "https://i.ibb.co/tQxwcnC/00044-4181393012-copy.png"
    ],
    "title": "devayani",
    "pg": "21"
  },
  {
    "images": [
      "https://i.ibb.co/HPYdXX5/7161416.jpg",
      "https://i.ibb.co/23MgqMj/00007-2141721006-copy.png"
    ],
    "title": "jayaprada",
    "pg": "21"
  },
  {
    "images": [
      "https://i.ibb.co/18LJ6Cn/00010-307253188-copy.png",
      "https://i.ibb.co/txjsY55/krishcasanova-20210312-0013.jpg"
    ],
    "title": "sneha paul free image hosting",
    "pg": "22"
  },
  {
    "images": ["https://i.ibb.co/svLDbcd/00008-1929845624-copy.png"],
    "title": "",
    "pg": "22"
  },
  {
    "images": [
      "https://i.ibb.co/YpTLFGD/20230307-140334.jpg",
      "https://i.ibb.co/VwqNXnW/00003-824063342-copy.png"
    ],
    "title": "anushka shetty",
    "pg": "22"
  },
  {
    "images": [
      "https://i.ibb.co/VCC2r4p/00000-2368588646-copy.png",
      "https://i.ibb.co/2NRtgc6/keerthysureshofficial-20230518-21.jpg"
    ],
    "title": "Keerthi suresh",
    "pg": "22"
  },
  {
    "images": [
      "https://i.ibb.co/yhjLHBx/dharshagupta-20230518-11.jpg",
      "https://i.ibb.co/L6vdW5t/00001-221845884-copy.png"
    ],
    "title": "Dharsha Gupta",
    "pg": "22"
  },
  {
    "images": [
      "https://i.ibb.co/Hhst6CF/anusree-luv-20230518-7.jpg",
      "https://i.ibb.co/ydRFRzS/00002-458228516-copy.png"
    ],
    "title": "anusree-luv",
    "pg": "22"
  },
  {
    "images": [
      "https://i.ibb.co/m0P00kB/srinisha-jayaseelan-20230518-3.jpg",
      "https://i.ibb.co/3RfFFs5/00003-1466252010-copy.png"
    ],
    "title": "srinisha-jayaseelan",
    "pg": "22"
  },
  {
    "images": [
      "https://i.ibb.co/GTz7rBh/actresskasthuri-20230517-22.jpg",
      "https://i.ibb.co/VmJ0Lfh/00004-1403066193-copy.png"
    ],
    "title": "kasturi",
    "pg": "22"
  },
  {
    "images": [
      "https://i.ibb.co/z4tphJZ/pranikadhakshu-20230517-10.jpg",
      "https://i.ibb.co/2cgK2F7/00008-528611383-copy.png",
      "https://i.ibb.co/s9yDZF6/00006-565096675-copy.png"
    ],
    "title": "pranikadhakshu",
    "pg": "22"
  },
  {
    "images": [
      "https://i.ibb.co/RPHhLJx/pranikadhakshu-20230517-16.jpg",
      "https://i.ibb.co/j6YLYFy/00009-330201409-copy.png"
    ],
    "title": "pranikadhakshu",
    "pg": "22"
  },
  {
    "images": [
      "https://i.ibb.co/pPf2sxN/iswarya-menon-20230517-20.jpg",
      "https://i.ibb.co/kG3knkj/00007-2783391632-copy.png"
    ],
    "title": "iswarya-menon",
    "pg": "22"
  },
  {
    "images": [
      "https://i.ibb.co/hctqM69/gayathri-yuvraaj-20230517-9.jpg",
      "https://i.ibb.co/yQsfj79/00010-3937599492-copy.png"
    ],
    "title": "gayathri-yuvraaj",
    "pg": "22"
  },
  {
    "images": [
      "https://i.ibb.co/dbLPYhZ/samyukthamenon-20230517-17.jpg",
      "https://i.ibb.co/W3Fjhpr/00011-1091025002-copy.png"
    ],
    "title": "samyukthamenon",
    "pg": "22"
  },
  {
    "images": [
      "https://i.ibb.co/M6TCZ9C/sadaa17-20230517-6.jpg",
      "https://i.ibb.co/6rCSqkQ/00012-3405359405-copy.png"
    ],
    "title": "sadha",
    "pg": "22"
  },
  {
    "images": [
      "https://i.ibb.co/nnN8r34/sadaa17-20230517-7.jpg",
      "https://i.ibb.co/PwWH9DN/00016-1528454815-copy.png"
    ],
    "title": "Sadha thing 1 and 2 png",
    "pg": "22"
  },
  {
    "images": [
      "https://i.ibb.co/C1d5swr/samyuktha-shan-20230515-37.jpg",
      "https://i.ibb.co/Dz7pNxq/00015-2863385436-copy.png"
    ],
    "title": "Samyuktha Shanmughanathan photo banner website",
    "pg": "22"
  },
  {
    "images": [
      "https://i.ibb.co/6bH3Pv1/samyuktha-shan-20230515-36.jpg",
      "https://i.ibb.co/wKP3n3T/00017-2027561855-copy.png"
    ],
    "title": "Samyuktha Shanmughanathan best image app",
    "pg": "23"
  },
  {
    "images": [
      "https://i.ibb.co/yFhN36C/divyabharathioffl-20230515-31.jpg",
      "https://i.ibb.co/KK7XBH1/00018-3198816890-copy.png"
    ],
    "title": "2019 images download",
    "pg": "23"
  },
  {
    "images": [
      "https://i.ibb.co/WkNQQ89/divyabharathioffl-20230515-28.jpg",
      "https://i.ibb.co/D9fYLb8/00019-3072432227-copy.png"
    ],
    "title": "divyabharathi",
    "pg": "23"
  },
  {
    "images": [
      "https://i.ibb.co/kS8XTtR/nanthu-6624-20230515-24.jpg",
      "https://i.ibb.co/c2gBNds/00020-1542535363-copy.png"
    ],
    "title": "nanthu thevidiya munda",
    "pg": "23"
  },
  {
    "images": [
      "https://i.ibb.co/F49rkB5/janany-kj-20230514-8.jpg",
      "https://i.ibb.co/9ygYJZX/00021-3297859576-copy.png"
    ],
    "title": "janany picture post",
    "pg": "23"
  },
  {
    "images": [
      "https://i.ibb.co/DYLccpY/nidhhiagerwal-20230514-7.jpg",
      "https://i.ibb.co/kh72dTG/00022-3931598353-copy.png"
    ],
    "title": "Nidh i agerwal",
    "pg": "23"
  },
  {
    "images": [
      "https://i.ibb.co/cYD6Hnb/janani-ashokkumar-20230514-10.jpg",
      "https://i.ibb.co/Xbq8YzX/00023-2592883890-copy.png"
    ],
    "title": "",
    "pg": "23"
  },
  {
    "images": [
      "https://i.ibb.co/C2SXd1D/janani-ashokkumar-20230514-12.jpg",
      "https://i.ibb.co/x6p4NJw/00024-1569884468-copy.png"
    ],
    "title": "janani ashokkumar",
    "pg": "23"
  },
  {
    "images": [
      "https://i.ibb.co/ZWyr38Y/janani-ashokkumar-20230514-9.jpg",
      "https://i.ibb.co/v1YLGjV/00025-3514185991-copy.png"
    ],
    "title": "janani ashokkumar",
    "pg": "23"
  },
  {
    "images": [
      "https://i.ibb.co/wN74ZKQ/dharshagupta-20230514-3.jpg",
      "https://i.ibb.co/sgHt9N3/00026-1350011203-copy.png"
    ],
    "title": "Dharsha Gupta",
    "pg": "23"
  },
  {
    "images": [
      "https://i.ibb.co/Ht4kvsK/dharshagupta-20230514-2.jpg",
      "https://i.ibb.co/7ns5YSx/00027-1002000106-copy.png"
    ],
    "title": "Dharsha Gupta",
    "pg": "23"
  },
  {
    "images": [
      "https://i.ibb.co/wN74ZKQ/dharshagupta-20230514-3.jpg",
      "https://i.ibb.co/zJqXct5/00028-532459910-copy.png"
    ],
    "title": "Dharsha Gupta",
    "pg": "23"
  },
  {
    "images": [
      "https://i.ibb.co/d6LZ0D7/amritha-aiyer-20230513-8.jpg",
      "https://i.ibb.co/wcccW85/00029-365872393-copy.png"
    ],
    "title": "amritha-aiyer",
    "pg": "23"
  },
  {
    "images": [
      "https://i.ibb.co/rbsjqK7/niyah-krishna-20230513-6.jpg",
      "https://i.ibb.co/88MS3pB/00030-3708971126-copy.png"
    ],
    "title": "niyah-krishna",
    "pg": "23"
  },
  {
    "images": [
      "https://i.ibb.co/8cVvhFC/chaitrareddy-official-20230512-22.jpg",
      "https://i.ibb.co/JyJpBML/00034-3481162201-copy.png",
      "https://i.ibb.co/jW1s57q/00032-2983280702-copy.png"
    ],
    "title": "",
    "pg": "23"
  },
  {
    "images": [
      "https://i.ibb.co/XSz4NgK/chaitrareddy-official-20230512-20.jpg",
      "https://i.ibb.co/5BV24zR/00037-1334699883-copy.png",
      "https://i.ibb.co/Tqj4cJj/00035-2689894309-copy.png",
      "https://i.ibb.co/LP7Rv8z/00033-1504648345-copy.png"
    ],
    "title": "chaitra reddy",
    "pg": "23"
  },
  {
    "images": [
      "https://i.ibb.co/mzNH2VR/gayathri-yuvraaj-20230513-2.jpg",
      "https://i.ibb.co/TM31QKm/00036-3554174448-copy.png"
    ],
    "title": "gayathri-yuvraaj",
    "pg": "23"
  },
  {
    "images": [
      "https://i.ibb.co/ZX4jqj7/srinisha-jayaseelan-20230512-15.jpg",
      "https://i.ibb.co/2Smwnqj/00042-780451901-copy.png"
    ],
    "title": "srinisha-jayaseelan short poems about animals funny",
    "pg": "23"
  },
  {
    "images": [
      "https://i.ibb.co/SyXdmww/srinisha-jayaseelan-20230512-14.jpg",
      "https://i.ibb.co/7pQ3Nfm/00045-1932062202-copy.png"
    ],
    "title": "srinisha-jayaseelan",
    "pg": "24"
  },
  {
    "images": [
      "https://i.ibb.co/z5xz1gs/maanasi-k-20230512-16.jpg",
      "https://i.ibb.co/S3XC80z/00041-1222982211-copy.png"
    ],
    "title": "maanasi",
    "pg": "24"
  },
  {
    "images": [
      "https://i.ibb.co/g7YyF3V/pavithra-janani-20230512-25.jpg",
      "https://i.ibb.co/zm2V1GK/00039-3205877494-copy.png"
    ],
    "title": "pavithra-janani",
    "pg": "24"
  },
  {
    "images": [
      "https://i.ibb.co/cNSTRr1/desktop-wallpaper-avantika-mishra.jpg",
      "https://i.ibb.co/vvNWYfQ/00018-2863402950-copy.png"
    ],
    "title": "Avantika Mishra",
    "pg": "24"
  },
  {
    "images": [
      "https://i.ibb.co/dkGGNcL/desktop-wallpaper-tridha-choudhury-hot-saree-mobile-bella-rolland.jpg",
      "https://i.ibb.co/mXzJ9YM/00020-2546692800-copy.png"
    ],
    "title": "Tridha Choudhury",
    "pg": "24"
  },
  {
    "images": [
      "https://i.ibb.co/TLn1SLS/yIwgb.jpg",
      "https://i.ibb.co/r0883X8/00007-3746725361-copy.png"
    ],
    "title": "Soundblaze aka my monitor size",
    "pg": "24"
  },
  {
    "images": [
      "https://i.ibb.co/84pndvB/desktop-wallpaper-9-avantika-mishra-hot-for-mobile-avantika-mishra.jpg",
      "https://i.ibb.co/YkVSD1W/00011-1033422718-copy.png"
    ],
    "title": "Avantika Mishra",
    "pg": "24"
  },
  {
    "images": [
      "https://i.ibb.co/FgP4Xrm/Avantika-Mishra-8.jpg",
      "https://i.ibb.co/4RD4h9h/00012-1253466601-copy.png"
    ],
    "title": "Avantika Mishra",
    "pg": "24"
  },
  {
    "images": [
      "https://i.ibb.co/rFpFP9L/desktop-wallpaper-avantika-mishra-telugu-actres.jpg",
      "https://i.ibb.co/FnMr4W4/00013-1438811178-copy.png"
    ],
    "title": "Avantika Mishra",
    "pg": "24"
  },
  {
    "images": [
      "https://i.ibb.co/xHwwYFY/IMG-20230523-234839-908.jpg",
      "https://i.ibb.co/0CXBxLR/00010-2162811528-copy.png"
    ],
    "title": "Avantika Mishra",
    "pg": "24"
  },
  {
    "images": [
      "https://i.ibb.co/rFMjgXw/yI7h8.jpg",
      "https://i.ibb.co/ByV22hL/00005-2207579927-copy.png"
    ],
    "title": "Soundblaze aka",
    "pg": "25"
  },
  {
    "images": [
      "https://i.ibb.co/GPF6bdm/yI2Vp.jpg",
      "https://i.ibb.co/60rvdQv/00004-2063094825-copy.png"
    ],
    "title": "Soundblaze aka view screen size",
    "pg": "25"
  },
  {
    "images": [
      "https://i.ibb.co/WxWCgNW/rascb.jpg",
      "https://i.ibb.co/2hXb4M7/00003-619735014-copy.png"
    ],
    "title": "Soundblaze aka",
    "pg": "25"
  },
  {
    "images": [
      "https://i.ibb.co/C7JdC0C/rabp8.jpg",
      "https://i.ibb.co/kg9QSP7/00002-1117781773-copy.png"
    ],
    "title": "Soundblaze aka",
    "pg": "25"
  },
  {
    "images": [
      "https://i.ibb.co/WxWCgNW/rascb.jpg",
      "https://i.ibb.co/mtbzwyW/00001-2356519404-copy.png"
    ],
    "title": "Soundblaze aka",
    "pg": "25"
  },
  {
    "images": [
      "https://i.ibb.co/vdZjyNC/gayathri-shan-latest-hot-hd-photos-wallpapers-1080p-instagram-neep.jpg",
      "https://i.ibb.co/8m1D1C8/00000-4031946425-copy.png"
    ],
    "title": "",
    "pg": "25"
  },
  {
    "images": [
      "https://i.ibb.co/3BtD4DH/gayathri-shan-latest-hot-hd-photos-wallpapers-1080p-instagram-fpzi.jpg",
      "https://i.ibb.co/JC5t5KR/00002-3822347488-copy.png"
    ],
    "title": "gayathri shan download high quality pictures from instagram",
    "pg": "25"
  },
  {
    "images": [
      "https://i.ibb.co/F3QvbqM/gayathri-shan-latest-hot-hd-photos-wallpapers-1080p-instagram-ysqc.jpg",
      "https://i.ibb.co/3mF9BdN/00003-2582841362-copy.png"
    ],
    "title": "gayathri shan",
    "pg": "25"
  },
  {
    "images": [
      "https://i.ibb.co/r6PgT98/aparna-das-latest-hot-hd-photos-wallpapers-1080p-instagram-omgf.jpg",
      "https://i.ibb.co/xCR8NmR/00004-353544183-copy.png"
    ],
    "title": "aparna-das",
    "pg": "25"
  },
  {
    "images": [
      "https://i.ibb.co/d5vrhWF/aparna-das-latest-hot-hd-photos-wallpapers-1080p-instagram-wiap.jpg",
      "https://i.ibb.co/QDyv4Y9/00005-2846779183-copy.png"
    ],
    "title": "aparna-das",
    "pg": "25"
  },
  {
    "images": [
      "https://i.ibb.co/PjbXs9c/aparna-das-latest-hot-hd-photos-wallpapers-1080p-instagram-mxod.jpg",
      "https://i.ibb.co/Ydxws2G/00006-2106352710-copy.png"
    ],
    "title": "aparna-das",
    "pg": "25"
  },
  {
    "images": [
      "https://i.ibb.co/dfPvZ6K/meet-miya-20230328-26.jpg",
      "https://i.ibb.co/GFnFJP8/00007-453534389-copy.png"
    ],
    "title": "meet-miya",
    "pg": "25"
  },
  {
    "images": [
      "https://i.ibb.co/d21k1js/nivethapethuraj-love-20230328-18.jpg",
      "https://i.ibb.co/Qbb5ZYW/00008-1343002152-copy.png"
    ],
    "title": "nivethapethuraj",
    "pg": "25"
  },
  {
    "images": [
      "https://i.ibb.co/swKgGyz/sujithadhanush-20230406-11.jpg",
      "https://i.ibb.co/DWQrYSS/00009-2955592355-copy.png"
    ],
    "title": "sujithadhanush",
    "pg": "25"
  },
  {
    "images": [
      "https://i.ibb.co/c3Tf1jN/saidhanshika-20230408-49.jpg",
      "https://i.ibb.co/m4NLbqt/00012-2261609638-copy.png",
      "https://i.ibb.co/0fLBM9s/00010-1337188298-copy.png"
    ],
    "title": "saidhanshika",
    "pg": "25"
  },
  {
    "images": [
      "https://i.ibb.co/vYvyT9c/sujithadhanush-20230414-23.jpg",
      "https://i.ibb.co/BCM7FNd/00011-2225638997-copy.png"
    ],
    "title": "sujithadhanush",
    "pg": "25"
  },
  {
    "images": [
      "https://i.ibb.co/fMVsq3x/yours-anjali-20230414-41.jpg",
      "https://i.ibb.co/G7rM8TZ/00013-3387237172-copy.png"
    ],
    "title": "Anjali",
    "pg": "25"
  },
  {
    "images": [
      "https://i.ibb.co/VqYSWvw/gabriellacharlton-20230419-3.jpg",
      "https://i.ibb.co/cDq3KCC/00014-1089425019-copy.png"
    ],
    "title": "gabriellacharlton",
    "pg": "25"
  },
  {
    "images": [
      "https://i.ibb.co/SNhwTqb/sujithadhanush-20230502-23.jpg",
      "https://i.ibb.co/NLVGBfH/00017-1905493712-copy.png",
      "https://i.ibb.co/55bKzYr/00015-3648257807-copy.png"
    ],
    "title": "sujithadhanush how to download pictures from instagram online",
    "pg": "25"
  },
  {
    "images": [
      "https://i.ibb.co/DtzYpCj/sujithadhanush-20230506-1.jpg",
      "https://i.ibb.co/R2CXpvt/00016-2271090821-copy.png"
    ],
    "title": "sujithadhanush",
    "pg": "25"
  },
  {
    "images": [
      "https://i.ibb.co/VgN0TJx/gabriellacharlton-20230510-89.jpg",
      "https://i.ibb.co/Xs6JVBh/00018-2569286013-copy.png"
    ],
    "title": "gabriellacharlton",
    "pg": "26"
  },
  {
    "images": [
      "https://i.ibb.co/J292fKp/iamaathmikaa-20230511-30.jpg",
      "https://i.ibb.co/6vJCk04/00019-2116502445-copy.png"
    ],
    "title": "Avanthika",
    "pg": "26"
  },
  {
    "images": [
      "https://i.ibb.co/VJ8jd19/neelimaesai-20230511-15-1.jpg",
      "https://i.ibb.co/h2mxFbj/00020-1815542691-copy.png"
    ],
    "title": "nelima",
    "pg": "26"
  },
  {
    "images": [
      "https://i.ibb.co/jJg4ztM/neelimaesai-20230511-13.jpg",
      "https://i.ibb.co/XbqhvJt/00021-3716677064-copy.png"
    ],
    "title": "nelima",
    "pg": "26"
  },
  {
    "images": [
      "https://i.ibb.co/ykbM7xt/gayathri-shan-latest-hot-hd-photos-wallpapers-1080p-instagram-kx9c.jpg",
      "https://i.ibb.co/8Bzzm69/00000-1679913270-copy.png"
    ],
    "title": "gayathri-shan picupload",
    "pg": "26"
  },
  {
    "images": [
      "https://i.ibb.co/YWzybZW/gayathri-shan-latest-hot-hd-photos-wallpapers-1080p-instagram-gszp.jpg",
      "https://i.ibb.co/yPY1dyc/00001-837359247-copy.png"
    ],
    "title": "gayathri-shan",
    "pg": "26"
  },
  {
    "images": [
      "https://i.ibb.co/K5ptBjX/nithyashree-20230406-44.jpg",
      "https://i.ibb.co/RbKnRm6/00002-93424168-copy.png"
    ],
    "title": "nithyashree host pictures",
    "pg": "26"
  },
  {
    "images": [
      "https://i.ibb.co/Y0BhRBw/himabindhu-20230407-37.jpg",
      "https://i.ibb.co/23QSTP9/00003-2738082337-copy.png"
    ],
    "title": "himabindhu",
    "pg": "26"
  },
  {
    "images": [
      "https://i.ibb.co/Jmdqb1W/itsvg-20230415-53.jpg",
      "https://i.ibb.co/XFDCySS/00007-2108379502-copy.png"
    ],
    "title": "",
    "pg": "26"
  },
  {
    "images": [
      "https://i.ibb.co/Hdh4HRP/janany-kj-20230418-29.jpg",
      "https://i.ibb.co/1LqJxgS/00008-3100265853-copy.png"
    ],
    "title": "janany-kj",
    "pg": "26"
  },
  {
    "images": [
      "https://i.ibb.co/CnSKqbQ/swathishta-krishnan-20230418-33.jpg",
      "https://i.ibb.co/x5jCbvf/00009-915093255-copy.png"
    ],
    "title": "swathishta-krishnan",
    "pg": "26"
  },
  {
    "images": [
      "https://i.ibb.co/cc0dwH4/sadaa17-20230425-26.jpg",
      "https://i.ibb.co/TgPm7fN/00010-1249779473-copy.png"
    ],
    "title": "sadha",
    "pg": "26"
  },
  {
    "images": [
      "https://i.ibb.co/PwLYFKZ/abhiramiact-20230429-11.jpg",
      "https://i.ibb.co/Q6KprD9/00011-828877751-copy.png"
    ],
    "title": "abhirami",
    "pg": "26"
  },
  {
    "images": [
      "https://i.ibb.co/2jq7J9z/gayathrishan-official-20230426-45.jpg",
      "https://i.ibb.co/Fw73dGJ/00012-1670901270-copy.png"
    ],
    "title": "gayathri-shan",
    "pg": "26"
  },
  {
    "images": [
      "https://i.ibb.co/yk78cqJ/mirnaliniravi-20230430-3.jpg",
      "https://i.ibb.co/gWmQ6BV/00014-1515228812-copy.png"
    ],
    "title": "mirnaliniravi",
    "pg": "26"
  },
  {
    "images": [
      "https://i.ibb.co/DCvGnqM/kaniha-official-20230511-38.jpg",
      "https://i.ibb.co/WV1q8t1/00015-2784297862-copy.png"
    ],
    "title": "kaniha",
    "pg": "27"
  },
  {
    "images": [
      "https://i.ibb.co/hY2JMCL/2srini-20230511-19.jpg",
      "https://i.ibb.co/L5FsrCM/00017-2265546806-copy.png"
    ],
    "title": "srini",
    "pg": "27"
  },
  {
    "images": [
      "https://i.ibb.co/gZp58pL/meena-forever-20230511-11.jpg",
      "https://i.ibb.co/wRKS5cd/00019-2064825026-copy.png"
    ],
    "title": "meena",
    "pg": "27"
  },
  {
    "images": [
      "https://i.ibb.co/7vv6LsQ/janhvi-kapoor-hot-hd-photos-mobile-wallpapers-1080p-2wp9.jpg",
      "https://i.ibb.co/kKnLM2m/00020-2193369837-copy.png"
    ],
    "title": "janhvi-kapoor image post",
    "pg": "27"
  },
  {
    "images": [
      "https://i.ibb.co/ZG8p65R/janhvi-kapoor-hot-hd-photos-mobile-wallpapers-1080p-7ziy.jpg",
      "https://i.ibb.co/nmJ8j4p/00021-1704405694-copy.png"
    ],
    "title": "janhvi-kapoor picture upload sites",
    "pg": "27"
  },
  {
    "images": [
      "https://i.ibb.co/M9PJSJk/wordsofsiva-20230429-23.jpg",
      "https://i.ibb.co/Fscxzh9/00035-1301860011-copy.png"
    ],
    "title": "trisha krishnan",
    "pg": "27"
  },
  {
    "images": [
      "https://i.ibb.co/zH60MZZ/swathishta-krishnan-20230502-17.jpg",
      "https://i.ibb.co/rF5Lttt/00038-605439582-copy.png"
    ],
    "title": "swathishta-krishnan",
    "pg": "27"
  },
  {
    "images": [
      "https://i.ibb.co/s2jm2D3/gabriellacharlton-20230429-17.jpg",
      "https://i.ibb.co/LPyQzd7/00039-2040206339-copy.png"
    ],
    "title": "gabriellacharlton",
    "pg": "27"
  },
  {
    "images": [
      "https://i.ibb.co/JQVVwWg/anusree-luv-20230418-88.jpg",
      "https://i.ibb.co/64TDxkC/00040-218977633-copy.png"
    ],
    "title": "anusree luv 2010 acura tl specs 0 60",
    "pg": "27"
  },
  {
    "images": [
      "https://i.ibb.co/HCxP6jc/himabindhu-20230418-73.jpg",
      "https://i.ibb.co/3zNLCmV/00041-3301631428-copy.png"
    ],
    "title": "himabindhu 2013 honda fit 0 60",
    "pg": "27"
  },
  {
    "images": [
      "https://i.ibb.co/gDbmZsx/srinisha-jayaseelan-20230502-26.jpg",
      "https://i.ibb.co/7rn5Dyr/00042-2261799231-copy.png"
    ],
    "title": "srinisha-jayaseelan legacy gt 0 60",
    "pg": "27"
  },
  {
    "images": [
      "https://i.ibb.co/PCG5gzD/Tattoo-of-G-clef-on-left-wrist-of-Kavyashree-Gowde.jpg",
      "https://i.ibb.co/ncrdSs4/00005-4282590779-copy.png"
    ],
    "title": "Kavyashree-Gowde",
    "pg": "28"
  },
  {
    "images": [
      "https://i.ibb.co/dGwqgnc/346812149-960465945307683-8584283147213167339-n.jpg",
      "https://i.ibb.co/LYyFP9m/00006-1756291302-copy.png"
    ],
    "title": "Kavyashree-Gowde",
    "pg": "28"
  },
  {
    "images": ["https://i.ibb.co/cT9kdFm/00009-4028096501-copy.png"],
    "title": "anithasampath https://i.ibb.co/8bMcfgh/official- [url=https://ibb.co/dPz46fN][img]https://i.ibb.co/jy1kG8C/00011-2826574450-copy.png-20230526-30.jpg[/img][/url]",
    "pg": "28"
  },
  {
    "images": [
      "https://i.ibb.co/w4n7wP9/swathishta-krishnan-20230526-31.jpg",
      "https://i.ibb.co/LNPCmGn/00014-2224446658-copy.png",
      "https://i.ibb.co/2MydDG9/00010-1667107434-copy.png"
    ],
    "title": "swathishta-krishnan",
    "pg": "28"
  },
  {
    "images": [
      "https://i.ibb.co/ydjc0Ls/vanibhojan-20230526-35.jpg",
      "https://i.ibb.co/hXMC3ww/00013-3327366812-copy.png"
    ],
    "title": "vanibhojan",
    "pg": "28"
  },
  {
    "images": [
      "https://i.ibb.co/JxSbXnc/official-anithasampath-20230526-27.jpg",
      "https://i.ibb.co/6BGkBM1/00019-2279987160-copy.png"
    ],
    "title": "anithasampath",
    "pg": "28"
  },
  {
    "images": [
      "https://i.ibb.co/XYGrbJw/pranikadhakshu-20230526-36.jpg",
      "https://i.ibb.co/BnJ16fL/00022-2116004822-copy.png"
    ],
    "title": "pranikadhakshu early harp 4 letters",
    "pg": "28"
  },
  {
    "images": [
      "https://i.ibb.co/g6ZFZBq/official-anithasampath-20230526-28.jpg",
      "https://i.ibb.co/NKRZG4M/00021-454733344-copy.png"
    ],
    "title": "anithasampath",
    "pg": "28"
  },
  {
    "images": [
      "https://i.ibb.co/fGV8BBd/raashiikhanna-20230526-22.jpg",
      "https://i.ibb.co/SNyGBww/00024-3777758835-copy.png"
    ],
    "title": "raashii khanna",
    "pg": "28"
  },
  {
    "images": [
      "https://i.ibb.co/56wgpyX/official-anithasampath-20230526-24.jpg",
      "https://i.ibb.co/vdxsSTj/00025-242000562-copy.png"
    ],
    "title": "anithasampath hockey's mikita crossword",
    "pg": "28"
  },
  {
    "images": [
      "https://i.ibb.co/QQBVPML/maanasi-k-20230526-18.jpg",
      "https://i.ibb.co/1XMVJZ5/00027-2112991716-copy.png",
      "https://i.ibb.co/XWNn44f/00026-162473537-copy.png"
    ],
    "title": "maanasi-k",
    "pg": "28"
  },
  {
    "images": [
      "https://i.ibb.co/MBzgQfG/shriya-saran1109-20230526-15.jpg",
      "https://i.ibb.co/72kT9bH/00028-1267578722-copy.png"
    ],
    "title": "shreya",
    "pg": "28"
  },
  {
    "images": [
      "https://i.ibb.co/tpH0SBY/malavikacmenon-20230526-12.jpg",
      "https://i.ibb.co/PjWqgH8/00029-3321050340-copy.png"
    ],
    "title": "malavikacmenon villains lament crossword",
    "pg": "28"
  },
  {
    "images": [
      "https://i.ibb.co/WxTzR2f/malavikacmenon-20230526-9.jpg",
      "https://i.ibb.co/gt1vHp9/00030-558673250-copy.png"
    ],
    "title": "malavikacmenon",
    "pg": "28"
  },
  {
    "images": [
      "https://i.ibb.co/2gsHsZz/malavikamohanan-20230526-3.jpg",
      "https://i.ibb.co/YL9dz1N/00031-1307682877-copy.png"
    ],
    "title": "malavikamohanan",
    "pg": "28"
  },
  {
    "images": [
      "https://i.ibb.co/MgMBWBc/malavikamohanan-20230526-6.jpg",
      "https://i.ibb.co/cbs8QBw/00032-2536092647-copy.png"
    ],
    "title": "malavikamohanan",
    "pg": "28"
  },
  {
    "images": [
      "https://i.ibb.co/mNyHz0W/iamsamyukthaa-20230525-36.jpg",
      "https://i.ibb.co/hCm584Q/00033-3854016852-copy.png"
    ],
    "title": "samyukthaa",
    "pg": "28"
  },
  {
    "images": [
      "https://i.ibb.co/yX79vBj/iamsamyukthaa-20230525-33.jpg",
      "https://i.ibb.co/p31nhgm/00034-1041848727-copy.png"
    ],
    "title": "samyukthaa rudner and moreno",
    "pg": "28"
  },
  {
    "images": [
      "https://i.ibb.co/Dz6H16y/vj-archana-20230525-28.jpg",
      "https://i.ibb.co/XFzvFVJ/00035-1267883658-copy.png"
    ],
    "title": "vj-archana-",
    "pg": "28"
  },
  {
    "images": [
      "https://i.ibb.co/gDND9wf/janhvikapoor-20230525-16.jpg",
      "https://i.ibb.co/p4M0P1L/00037-2321938172-copy.png"
    ],
    "title": "janhvikapoor",
    "pg": "29"
  },
  {
    "images": [
      "https://i.ibb.co/qnzfhBf/chaitrareddy-official-20230525-29.jpg",
      "https://i.ibb.co/VgnMcd9/00038-3324964390-copy.png"
    ],
    "title": "chaitrareddy",
    "pg": "29"
  },
  {
    "images": [
      "https://i.ibb.co/wCLVKPx/chaitra-reddy-hot-hd-photos-wallpapers-for-mobile-whatsapp-uvgx.jpg",
      "https://i.ibb.co/qBnH0M3/00000-1801973628-copy.png"
    ],
    "title": "chaitra reddy city of refuge atlanta",
    "pg": "29"
  },
  {
    "images": [
      "https://i.ibb.co/Gt5q81k/00001-4241049383-copy.png",
      "https://i.ibb.co/Fmrqt05/manju-warrier-20230523-11.jpg"
    ],
    "title": "manju-warrier",
    "pg": "29"
  },
  {
    "images": [
      "https://i.ibb.co/cgSdTdF/00002-4293691073-copy.png",
      "https://i.ibb.co/4P9MKQ2/iamsruthiraj-20230521-33.jpg"
    ],
    "title": "sruthiraj",
    "pg": "29"
  },
  {
    "images": ["https://i.ibb.co/dDjd9pV/00003-2320313992-copy.png"],
    "title": "shreya ghoshal eva vaila poola vettu aattanum upload image and get link",
    "pg": "29"
  },
  {
    "images": [
      "https://i.ibb.co/253WjKZ/00004-2816466131-copy.png",
      "https://i.ibb.co/rb76ryZ/athulyaofficial-20230521-37.jpg"
    ],
    "title": "online upload photos",
    "pg": "29"
  },
  {
    "images": [
      "https://i.ibb.co/T8V4xVF/shreya-ghoshal-beautiful-hd-photos-mobile-wallpapers-hd-androidiphone-sbss.jpg",
      "https://i.ibb.co/N2Tfxq5/00005-2380265227-copy.png"
    ],
    "title": "shreya ghoshal thevidiya mundaiya sing pannitu erukum potheaa okanum",
    "pg": "29"
  },
  {
    "images": [
      "https://i.ibb.co/zRQBPZX/deepabalu-official-20230521-50.jpg",
      "https://i.ibb.co/NV99XxZ/00007-1020060050-copy.png"
    ],
    "title": "deepabalu",
    "pg": "29"
  },
  {
    "images": [
      "https://i.ibb.co/N6ZP284/shivani-narayanan-20230519-27.jpg",
      "https://i.ibb.co/ZzfsXC6/00009-635175863-copy.png"
    ],
    "title": "shivani narayanan",
    "pg": "29"
  },
  {
    "images": [
      "https://i.ibb.co/8zGwb0z/shreya-ghoshal-beautiful-hd-photos-mobile-wallpapers-hd-androidiphone-ozgp.jpg",
      "https://i.ibb.co/dbBhT19/00010-2368988269-copy.png"
    ],
    "title": "shreya ghoshal",
    "pg": "29"
  },
  {
    "images": [
      "https://i.ibb.co/xqRKHRn/gabriellacharlton-20230521-19.jpg",
      "https://i.ibb.co/LYfW4Hg/00011-204612887-copy.png"
    ],
    "title": "gabriella charlton",
    "pg": "29"
  },
  {
    "images": [
      "https://i.ibb.co/pRLPGZP/srinisha-jayaseelan-beautiful-hd-photos-mobile-wallpapers-hd-androidiphone-rnod.jpg",
      "https://i.ibb.co/WBDZSyv/00014-852972947-copy.png",
      "https://i.ibb.co/PQ5vXHD/00012-14559934-copy.png"
    ],
    "title": "srinisha jayaseelan",
    "pg": "29"
  },
  {
    "images": [
      "https://i.ibb.co/Rc1h4RQ/malavikacmenon-20230519-18.jpg",
      "https://i.ibb.co/W3kvyYN/00015-593872642-copy.png"
    ],
    "title": "malavikac menon",
    "pg": "29"
  },
  {
    "images": [
      "https://i.ibb.co/NtKytCR/niyah-krishna-20230522-15.jpg",
      "https://i.ibb.co/gJdXjNg/00017-3494886556-copy.png"
    ],
    "title": "niya krishna dedupe list",
    "pg": "29"
  },
  {
    "images": [
      "https://i.ibb.co/BVCJRJX/rakulpreet-20230519-19.jpg",
      "https://i.ibb.co/qMX0cpm/00018-3968113002-copy.png"
    ],
    "title": "rakul preet",
    "pg": "30"
  },
  {
    "images": [
      "https://i.ibb.co/8msYX7r/shivani-narayananbigg-boss-latest-hot-hd-photos-wallpapers-1080p-r9vx.jpg",
      "https://i.ibb.co/JnXvhzB/00019-3329694522-copy.png"
    ],
    "title": "shivani narayanan find duplicates online",
    "pg": "30"
  },
  {
    "images": [
      "https://i.ibb.co/Lnvs21V/shivani-narayananbigg-boss-latest-hot-hd-photos-wallpapers-1080p-p3bn.jpg",
      "https://i.ibb.co/HTYkskb/00020-4153126567-copy.png"
    ],
    "title": "shivani narayanan",
    "pg": "30"
  },
  {
    "images": [
      "https://i.ibb.co/xY4dGgJ/sujithadhanush-20230521-9.jpg",
      "https://i.ibb.co/cCZyPgq/00021-2347479593-copy.png"
    ],
    "title": "sujitha dhanush",
    "pg": "30"
  },
  {
    "images": [
      "https://i.ibb.co/m9xW2kC/niyah-krishna-20230519-4.jpg",
      "https://i.ibb.co/7tjVPbD/00022-393200399-copy.png"
    ],
    "title": "niyah krishna",
    "pg": "30"
  },
  {
    "images": [
      "https://i.ibb.co/cJvyrxL/malavikacmenon-20230519-15.jpg",
      "https://i.ibb.co/BTYs6tn/00024-1654947171-copy.png"
    ],
    "title": "malavika menon",
    "pg": "30"
  },
  {
    "images": [
      "https://i.ibb.co/cD3hnqX/sadaa17-20230525-2.jpg",
      "https://i.ibb.co/GTNKp4t/00025-971056334-copy.png"
    ],
    "title": "sadha",
    "pg": "30"
  },
  {
    "images": [
      "https://i.ibb.co/PY9yCYG/jilla9.jpg",
      "https://i.ibb.co/nm297t4/00026-2914975294-copy.png"
    ],
    "title": "kajal agarwal",
    "pg": "30"
  },
  {
    "images": [
      "https://i.ibb.co/SyVnmm9/chaitra-reddy-hot-hd-photos-wallpapers-for-mobile-whatsapp-tndc.jpg",
      "https://i.ibb.co/8zyFj8q/00027-3638814693-copy.png"
    ],
    "title": "chaitra reddy",
    "pg": "30"
  },
  {
    "images": [
      "https://i.ibb.co/m4C6TXD/00029-2251096087-copy.png",
      "https://i.ibb.co/HN45h8T/srinisha-jayaseelan-beautiful-hd-photos-mobile-wallpapers-hd-androidiphone-krmf.jpg"
    ],
    "title": "srinisha jayaseelan livecode json",
    "pg": "30"
  },
  {
    "images": [
      "https://i.ibb.co/n3bKyzj/kajalagarwal9.jpg",
      "https://i.ibb.co/vXd5LPV/00030-3971221754-copy.png"
    ],
    "title": "kajal agarwal",
    "pg": "30"
  },
  {
    "images": [
      "https://i.ibb.co/1skj0XL/kajalagarwal2.jpg",
      "https://i.ibb.co/HVd0MSd/00034-2013288143-copy.png"
    ],
    "title": "kajal agarwal",
    "pg": "30"
  },
  {
    "images": [
      "https://i.ibb.co/nRVrT5C/kajal-agarwal1.jpg",
      "https://i.ibb.co/x5mrS6n/00035-307736523-copy.png"
    ],
    "title": "kajal agarwal",
    "pg": "30"
  },
  {
    "images": [
      "https://i.ibb.co/0Ygqwtq/kajalagarwal47.jpg",
      "https://i.ibb.co/RzJkj4M/00036-1522261685-copy.png"
    ],
    "title": "kajal agarwal",
    "pg": "30"
  },
  {
    "images": [
      "https://i.ibb.co/60pyRC5/kajal-agarwal7.jpg",
      "https://i.ibb.co/zZhvd6n/00038-1268334498-copy.png"
    ],
    "title": "kajal agarwal",
    "pg": "30"
  },
  {
    "images": [
      "https://i.ibb.co/hB76G0M/kajal-agarwal6.jpg",
      "https://i.ibb.co/61zbH9J/00039-32185864-copy.png"
    ],
    "title": "kajal agarwal free geojson data",
    "pg": "30"
  },
  {
    "images": [
      "https://i.ibb.co/8M1gfRD/kajalagarwal1.jpg",
      "https://i.ibb.co/W6rqRDQ/00040-2735821524-copy.png"
    ],
    "title": "kajal agarwal",
    "pg": "30"
  },
  {
    "images": [
      "https://i.ibb.co/QmhTgfF/priyanka-mohan-sreekaram-grand-release4.jpg",
      "https://i.ibb.co/9cmcfwr/00042-1315185556-copy.png"
    ],
    "title": "priyanka mohan",
    "pg": "30"
  },
  {
    "images": ["https://i.ibb.co/r3Wh4b6/00044-2686642652-copy.png"],
    "title": "keerthy suresh",
    "pg": "30"
  },
  {
    "images": [
      "https://i.ibb.co/QPHt88D/keerthy-suresh-gandhari-musical-song-launch12.jpg",
      "https://i.ibb.co/3shNKWt/00045-2414474994-copy.png"
    ],
    "title": "keerthy suresh json checker google",
    "pg": "30"
  },
  {
    "images": [
      "https://i.ibb.co/fQ0yv3K/ragada-anushka-hot-saree-pics-1352.jpg",
      "https://i.ibb.co/LnhHpW9/00047-1670832416-copy.png"
    ],
    "title": "anushka shetty",
    "pg": "31"
  },
  {
    "images": [
      "https://i.ibb.co/30pD1fj/anushka5.jpg",
      "https://i.ibb.co/cCPm4CL/00048-884460993-copy.png"
    ],
    "title": "anushka shetty",
    "pg": "31"
  },
  {
    "images": [
      "https://simgbb.com/images/favicon.png",
      "https://i.ibb.co/MpcWwM6/20230530-115321.jpg"
    ],
    "title": "20230530-115321 hosted at ImgBB Image 20230530-115321 hosted in ImgBB ibb.co Do this please \ud83d\ude4f",
    "pg": "31"
  },
  {
    "images": [
      "https://static.cdninstagram.com/rsrc.php/v3/yI/r/VsNE-OHk_8a.png"
    ],
    "title": "Login \u2022 Instagram Welcome back to Instagram. Sign in to check out what your friends, family & interests have been capturing & sharing around the world. instagram.com Please make her nude \ud83d\ude4f\ud83c\udffb",
    "pg": "32"
  },
  {
    "images": [
      "https://i.ibb.co/XzNVqwr/getimg-ai-2023-07-06-T14-04-10-326-Z.png",
      "https://i.ibb.co/M1Vjd3z/getimg-ai-2023-07-06-T14-04-04-302-Z.png",
      "https://i.ibb.co/8XJpZjW/getimg-ai-2023-07-06-T14-02-07-614-Z.png",
      "https://i.ibb.co/DgFV6cQ/getimg-ai-2023-07-06-T13-59-46-894-Z.png",
      "https://i.ibb.co/GpV9cMs/getimg-ai-2023-07-06-T13-59-39-373-Z.png"
    ],
    "title": "thank you for making this Dora image @mr.pink bull",
    "pg": "32"
  }
]
